adder_sub_4bit.v
module adder_sub_4bit (A,B,Ci,S,Co);

parameter data_size = 4;
input [data_size-1:0] A,B;
input Ci;
output [data_size-1:0] S;
output Co;
reg [data_size-1:0] S;
reg Co;

always @ (A or B or Ci)
    if (Ci)
        {Co,S} = A - B;
    else
        {Co,S} = A + B;
endmodule

adder_sub_4bit_tb.v
module tb_adder_sub_4bit;
    reg [3:0] A,B;
    reg Ci;
    wire [3:0] S;
    wire Co;

    adder_sub_4bit DUT (
        .A(A),
        .B(B),
        .Ci(Ci),
        .S(S),
        .Co(Co)    
    );

    initial begin
        $dumpfile("adder_sub_4bit.vcd");
        $dumpvars(0, tb_adder_sub_4bit);
    end

    initial begin 
        $monitor("Time=%0t  A=%b  B=%b  Ci=%b  |  S=%b  Co=%b",
        $time, A, B, Ci, S, Co);
    end

    initial begin
        A = 4'b0110; B = 4'b1001; Ci=0; #10;
        A = 4'b0110; B = 4'b1011; Ci=0; #10;
        A = 4'b0000; B = 4'b1001; Ci=0; #10;
        A = 4'b0000; B = 4'b0000; Ci=0; #10;
        A = 4'b0110; B = 4'b1111; Ci=0; #10;        
        A = 4'b0110; B = 4'b1001; Ci=1; #10;
        A = 4'b0110; B = 4'b1011; Ci=1; #10;
        A = 4'b0000; B = 4'b1001; Ci=1; #10;
        A = 4'b0000; B = 4'b0000; Ci=1; #10;
        A = 4'b0110; B = 4'b1111; Ci=1; #10;
        $finish;
    end
endmodule

adder_sub_4bit.vcd
$date
	Sat Dec 13 21:48:50 2025
$end
$version
	Icarus Verilog
$end
$timescale
	1s
$end
$scope module tb_adder_sub_4bit $end
$var wire 4 ! S [3:0] $end
$var wire 1 " Co $end
$var reg 4 # A [3:0] $end
$var reg 4 $ B [3:0] $end
$var reg 1 % Ci $end
$scope module DUT $end
$var wire 4 & A [3:0] $end
$var wire 4 ' B [3:0] $end
$var wire 1 % Ci $end
$var reg 1 " Co $end
$var reg 4 ( S [3:0] $end
$upscope $end
$upscope $end
$enddefinitions $end
#0
$dumpvars
b1111 (
b1001 '
b110 &
0%
b1001 $
b110 #
0"
b1111 !
$end
#10
1"
b1 !
b1 (
b1011 $
b1011 '
#20
0"
b1001 !
b1001 (
b1001 $
b1001 '
b0 #
b0 &
#30
b0 !
b0 (
b0 $
b0 '
#40
1"
b101 !
b101 (
b1111 $
b1111 '
b110 #
b110 &
#50
b1101 !
b1101 (
1%
b1001 $
b1001 '
#60
b1011 !
b1011 (
b1011 $
b1011 '
#70
b111 !
b111 (
b1001 $
b1001 '
b0 #
b0 &
#80
0"
b0 !
b0 (
b0 $
b0 '
#90
1"
b111 !
b111 (
b1111 $
b1111 '
b110 #
b110 &
