D_FF_NET_NRES.v
// this code is for D flip flip which is negative edge triggered with reset
module D_FF_NET_NRES(d_in, clk, n_res, q_out);

    input d_in, clk, n_res;
    output reg  q_out;


    always @(posedge clk or negedge n_res) begin

        if (~n_res)
            q_out <= 1'b0;
        else
            q_out <= d_in;
        
    end

endmodule

D_FF_NET_NRES_tb.v
module tb_D_FF_NET_NRES;

    reg d_in, clk, n_res;
    wire q_out;

    // Instantiate DUT
    D_FF_NET_NRES DUT (
        .d_in(d_in),
        .clk(clk),
        .n_res(n_res),
        .q_out(q_out)
    );

    // Clock generation (10 ns period)
    initial begin
        clk = 0;
        forever #5 clk = ~clk;
    end

    // VCD dump
    initial begin
        $dumpfile("D_FF_NET_NRES.vcd");
        $dumpvars(0, tb_D_FF_NET_NRES);
    end

    // Monitor
    initial begin
        $monitor("Time=%0t | clk=%b n_res=%b d_in=%b | q_out=%b",
                 $time, clk, n_res, d_in, q_out);
    end

    // Stimulus
    initial begin
        // Initial values
        d_in  = 0;
        n_res = 0;   // assert reset
        #12;

        n_res = 1;   // deassert reset
        #10;

        d_in = 1;    // captured at next posedge
        #10;

        d_in = 0;
        #10;

        d_in = 1;
        #10;

        // Assert reset asynchronously
        n_res = 0;
        #7;

        n_res = 1;
        d_in = 0;
        #20;

        $finish;
    end

endmodule

D_FF_NET_NRES.vcd
$date
	Wed Dec 24 00:56:46 2025
$end
$version
	Icarus Verilog
$end
$timescale
	1s
$end
$scope module tb_D_FF_NET_NRES $end
$var wire 1 ! q_out $end
$var reg 1 " clk $end
$var reg 1 # d_in $end
$var reg 1 $ n_res $end
$scope module DUT $end
$var wire 1 " clk $end
$var wire 1 # d_in $end
$var wire 1 $ n_res $end
$var reg 1 ! q_out $end
$upscope $end
$upscope $end
$enddefinitions $end
#0
$dumpvars
0$
0#
0"
0!
$end
#5
1"
#10
0"
#12
1$
#15
1"
#20
0"
#22
1#
#25
1!
1"
#30
0"
#32
0#
#35
0!
1"
#40
0"
#42
1#
#45
1!
1"
#50
0"
#52
0!
0$
#55
1"
#59
0#
1$
