D_FF_PLE.v
// D-FlpiFlop with positive level enable
module D_FF_PLE (D, LE, Q);
    input D,LE;
    output Q;
    reg Q;

    always @(D or LE) begin

        if (LE) begin
            Q <= D;
        end
        
    end

endmodule

D_FF_PLE_tb.v
module tb_D_FF_PLE ();
    reg D, LE;
    wire Q;

    D_FF_PLE DUT (
        .D(D),
        .LE(LE),
        .Q(Q)
    ); 

    initial begin
        $dumpfile("D_FF_PLE.vcd");
        $dumpvars(0, tb_D_FF_PLE);
    end

    initial begin
        $monitor("Time = %0t LE = %d  D = %d  |  Q = %d",
            $time, LE, D, Q);
    end

    initial begin
        #10;
        #10; LE = 0; D = 0;
        #10; LE = 1; D = 0;
        #10; LE = 1; D = 1;
        #10; LE = 1; D = 0;
        #10; LE = 1; D = 1;
        #10; LE = 0; D = 0;
        #10; LE = 0; D = 1;
        #10; LE = 1; D = 0;
        #10 $finish;
        
    end

endmodule

D_FF_PLE.vcd
$date
	Tue Dec 16 22:54:10 2025
$end
$version
	Icarus Verilog
$end
$timescale
	1s
$end
$scope module tb_D_FF_PLE $end
$var wire 1 ! Q $end
$var reg 1 " D $end
$var reg 1 # LE $end
$scope module DUT $end
$var wire 1 " D $end
$var wire 1 # LE $end
$var reg 1 ! Q $end
$upscope $end
$upscope $end
$enddefinitions $end
#0
$dumpvars
x#
x"
x!
$end
#20
0"
0#
#30
0!
1#
#40
1!
1"
#50
0!
0"
#60
1!
1"
#70
0"
0#
#80
1"
#90
0!
0"
1#
