decoder_3to8.v
module decoder_3to8 (X,En,Y);
    input [2:0] X;
    input En;
    output [7:0] Y;
    reg [7:0] Y;

    always @ (X or En)
    begin    
        if(En)
            case(X)
                3'b000 : Y = 8'b0000_0001;
                3'b001 : Y = 8'b0000_0010;
                3'b010 : Y = 8'b0000_0100;
                3'b011 : Y = 8'b0000_1000;
                3'b100 : Y = 8'b0001_0000;
                3'b101 : Y = 8'b0010_0000;
                3'b110 : Y = 8'b0100_0000;
                3'b111 : Y = 8'b1000_0000;
            endcase
        else
            Y = 8'b0000_0000;
    end
endmodule

decoder_3to8_tb.v
module tb_decoder_3to8;

    reg  [2:0] X;
    reg        En;
    wire [7:0] Y;

    // Instantiate DUT
    decoder_3to8 DUT (
        .X(X),
        .En(En),
        .Y(Y)
    );

    // VCD dump
    initial begin
        $dumpfile("decoder_3to8.vcd");
        $dumpvars(0, tb_decoder_3to8);
    end

    // Monitor output
    initial begin
        $monitor("Time=%0t  X=%b  En=%b  |  Y=%b", 
                  $time, X, En, Y);
    end

    // Apply test patterns
    initial begin
        En = 1;

        X = 3'b000; #10;
        X = 3'b001; #10;
        X = 3'b010; #10;
        X = 3'b011; #10;
        X = 3'b100; #10;
        X = 3'b101; #10;
        X = 3'b110; #10;
        X = 3'b111; #10;

        // Disable decoder
        En = 0;  X = 3'b101; #10;

        $finish;
    end

endmodule

decoder_3to8.vcd
$date
	Sat Dec 13 14:48:29 2025
$end
$version
	Icarus Verilog
$end
$timescale
	1s
$end
$scope module tb_decoder_3to8 $end
$var wire 8 ! Y [7:0] $end
$var reg 1 " En $end
$var reg 3 # X [2:0] $end
$scope module DUT $end
$var wire 1 " En $end
$var wire 3 $ X [2:0] $end
$var reg 8 % Y [7:0] $end
$upscope $end
$upscope $end
$enddefinitions $end
#0
$dumpvars
b1 %
b0 $
b0 #
1"
b1 !
$end
#10
b10 !
b10 %
b1 #
b1 $
#20
b100 !
b100 %
b10 #
b10 $
#30
b1000 !
b1000 %
b11 #
b11 $
#40
b10000 !
b10000 %
b100 #
b100 $
#50
b100000 !
b100000 %
b101 #
b101 $
#60
b1000000 !
b1000000 %
b110 #
b110 $
#70
b10000000 !
b10000000 %
b111 #
b111 $
#80
b0 !
b0 %
b101 #
b101 $
0"
