fifo_top.sv
`timescale 1ns/1ps

module fifo_top(
    input rst, clk, en, push_in, pop_in,
    input [7:0] din,
    output [7:0] dout,
    output empty, full, underrun, overrun,
    input [3:0] threshold,
    output th_trigger
);

reg [7:0] mem [0:15];
reg [3:0] waddr = 0;

logic push, pop;

reg empty_t;

always @(posedge clk , posedge rst) begin
    if(rst)
    empty_t <= 1'b0;
    else begin
        case({push, pop})
            2'b01: empty_t <= (~|(waddr) | ~en);
            2'b10: empty_t <= 1'b0;
        endcase
    end
end

reg full_t;

always @(posedge clk ,posedge rst) begin
    if(rst)
    full_t <= 1'b0;
    else begin
        case({push, pop})
            2'b01: full_t <= (&(waddr) | ~en);
            2'b10: full_t <= 1'b0; 
        endcase
    end
    
end

assign push = push_in & ~full_t;
assign pop = pop_in & ~ empty_t;


assign dout = mem[0];

always @(posedge clk, posedge rst ) begin
    if(rst)
    waddr <= 4'h0;
    else begin
        case({push, pop})
            2'b01:begin
                if(waddr != 4'hf && full_t == 1'b0)
                waddr <= waddr + 1;
                else
                waddr <= waddr;
            end
            2'b10:begin
                if (waddr != 4'h0 && empty_t == 1'b0) begin
                    waddr <= waddr - 1;
                end
                else
                waddr <= waddr;
            end
            default: ;
        endcase
    end
end

always @(posedge clk, posedge rst) begin
    case({push, pop})
    2'b01: begin //pop
        for(int i = 0; i < 14 ; i++) begin
            mem[i] <= mem[i+1];
        end
        mem[15] <= 8'h00;
    end
    2'b10: begin
        mem[waddr] <= din;
    end
    2'b11:begin
        for(int i = 0; i < 14; i++)begin
            mem[i] <= mem[i+1];
        end
        mem[15] <= 8'h00;
        mem[waddr-1] <= din;
    end
    endcase
end

//underrun
reg underrun_t;
always @(posedge clk, posedge rst ) begin
    if(rst)
    underrun_t <= 1'b0;
    else if (pop_in == 1'b1 && empty_t == 1'b1)
    underrun_t <= 1'b1;
    else
    underrun_t <=1'b0;
end

//overrun
reg overrun_t = 1'b0;
always @(posedge clk, posedge rst) begin
    if(rst)
    overrun_t <= 1'b0;
    else if (push_in == 1'b1 && full_t == 1'b1) begin
        overrun_t <= 1'b1;
    end
    else
    overrun_t <= 1'b0;
end

//threshold
reg thre_t;
always @(posedge clk, posedge rst) begin
    if(rst)
        thre_t <= 1'b0;
    else if(push ^ pop)
        thre_t <= (waddr >= threshold) ? 1'b1 : 1'b0;
    else
        thre_t <= 1'b0;

end


assign empty =  empty_t;
assign full = full_t;
assign underrun = underrun_t;
assign overrun = overrun_t;
assign th_trigger = thre_t;

endmodule



`timescale 1ns/1ps

module fifo_tb;

    // ============================================================
    // DUT signals
    // ============================================================

    reg        rst;
    reg        clk;
    reg        en;
    reg        push_in;
    reg        pop_in;
    reg [7:0]  din;

    wire [7:0] dout;
    wire       empty;
    wire       full;
    wire       underrun;
    wire       overrun;

    reg  [3:0] threshold;
    wire       th_trigger;


    // ============================================================
    // DUT
    // ============================================================

    fifo_top dut_fifo
    (
        .rst       (rst),
        .clk       (clk),
        .en        (en),
        .push_in   (push_in),
        .pop_in    (pop_in),
        .din       (din),
        .dout      (dout),
        .empty     (empty),
        .full      (full),
        .underrun  (underrun),
        .overrun   (overrun),
        .threshold (threshold),
        .th_trigger(th_trigger)
    );


    // ============================================================
    // Clock
    // 10 ns period
    // ============================================================

    always #5 clk = ~clk;


    // ============================================================
    // Test variables
    // ============================================================

    integer errors = 0;
    integer i;

    reg [7:0] expected;


    // ============================================================
    // VCD
    // ============================================================

    initial begin
        $dumpfile("fifo_top.vcd");
        $dumpvars(0, fifo_tb);
    end


    // ============================================================
    // MAIN TEST
    // ============================================================

    initial begin

        // --------------------------------------------------------
        // Initial values
        // --------------------------------------------------------

        clk       = 0;
        rst       = 1;
        en        = 0;
        push_in   = 0;
        pop_in    = 0;
        din       = 0;
        threshold = 4'd10;


        $display("");
        $display("============================================");
        $display("          FIFO SIMULATION START");
        $display("============================================");
        $display("");


        // ========================================================
        // RESET TEST
        // ========================================================

        $display("---- RESET TEST ----");

        repeat(3) @(posedge clk);

        rst = 0;
        en  = 1;

        @(posedge clk);

        $display("empty = %b, full = %b", empty, full);

        // NOTE:
        // A normal FIFO should have empty = 1 after reset.
        // Your current DUT sets empty_t = 0 during reset.
        // Therefore this check is expected to FAIL with your
        // current design.

        if (empty !== 1'b1) begin
            $display("WARNING: FIFO is not EMPTY after reset!");
            $display("         Current DUT gives empty = %b", empty);
            $display("");
        end
        else begin
            $display("RESET EMPTY CHECK : PASS");
        end


        // ========================================================
        // PUSH TEST
        // ========================================================

        $display("============================================");
        $display("             PUSH TEST");
        $display("============================================");

        for(i = 0; i < 5; i = i + 1)
        begin

            din     = 8'h10 + i;
            push_in = 1;
            pop_in  = 0;

            @(posedge clk);

            #1;

            $display("PUSH %0d : din = %h, dout = %h, count = %0d",
                     i,
                     din,
                     dout,
                     dut_fifo.waddr);
        end

        push_in = 0;

        @(posedge clk);


        // ========================================================
        // FIFO ORDER TEST
        // ========================================================

        $display("");
        $display("============================================");
        $display("          FIFO ORDER TEST");
        $display("============================================");

        for(i = 0; i < 5; i = i + 1)
        begin

            expected = 8'h10 + i;

            pop_in = 1;

            @(posedge clk);

            #1;

            if(dout === expected)
            begin
                $display("POP %0d : Expected = %h, Received = %h : PASS",
                         i,
                         expected,
                         dout);
            end
            else
            begin
                $display("POP %0d : Expected = %h, Received = %h : FAIL",
                         i,
                         expected,
                         dout);

                errors = errors + 1;
            end
        end

        pop_in = 0;


        // ========================================================
        // FULL TEST
        // ========================================================

        $display("");
        $display("============================================");
        $display("             FULL TEST");
        $display("============================================");

        // Push 16 elements
        for(i = 0; i < 16; i = i + 1)
        begin

            din     = 8'hA0 + i;
            push_in = 1;
            pop_in  = 0;

            @(posedge clk);

            #1;

            $display("PUSH %0d : din=%h full=%b",
                     i,
                     din,
                     full);
        end

        push_in = 0;

        @(posedge clk);

        if(full === 1'b1)
        begin
            $display("FULL CHECK : PASS");
        end
        else
        begin
            $display("FULL CHECK : FAIL");
            errors = errors + 1;
        end


        // ========================================================
        // OVERRUN TEST
        // ========================================================

        $display("");
        $display("============================================");
        $display("            OVERRUN TEST");
        $display("============================================");

        din     = 8'hFF;
        push_in = 1;
        pop_in  = 0;

        @(posedge clk);

        #1;

        if(overrun === 1'b1)
        begin
            $display("OVERRUN CHECK : PASS");
        end
        else
        begin
            $display("OVERRUN CHECK : FAIL");
            errors = errors + 1;
        end

        push_in = 0;


        // ========================================================
        // CLEAR FIFO BY POPPING
        // ========================================================

        $display("");
        $display("============================================");
        $display("           EMPTY / POP TEST");
        $display("============================================");

        pop_in = 1;

        for(i = 0; i < 16; i = i + 1)
        begin

            @(posedge clk);

            #1;

            $display("POP %0d : dout=%h empty=%b",
                     i,
                     dout,
                     empty);
        end

        pop_in = 0;

        @(posedge clk);

        if(empty === 1'b1)
        begin
            $display("EMPTY CHECK : PASS");
        end
        else
        begin
            $display("EMPTY CHECK : FAIL");
            errors = errors + 1;
        end


        // ========================================================
        // UNDERRUN TEST
        // ========================================================

        $display("");
        $display("============================================");
        $display("            UNDERRUN TEST");
        $display("============================================");

        pop_in = 1;

        @(posedge clk);

        #1;

        if(underrun === 1'b1)
        begin
            $display("UNDERRUN CHECK : PASS");
        end
        else
        begin
            $display("UNDERRUN CHECK : FAIL");
            errors = errors + 1;
        end

        pop_in = 0;


        // ========================================================
        // THRESHOLD TEST
        // ========================================================

        $display("");
        $display("============================================");
        $display("           THRESHOLD TEST");
        $display("============================================");

        threshold = 4'd5;

        for(i = 0; i < 6; i = i + 1)
        begin

            din     = 8'h50 + i;
            push_in = 1;
            pop_in  = 0;

            @(posedge clk);

            #1;

            $display("PUSH %0d : waddr=%0d threshold=%0d trigger=%b",
                     i,
                     dut_fifo.waddr,
                     threshold,
                     th_trigger);
        end

        push_in = 0;


        // ========================================================
        // FINAL RESULT
        // ========================================================

        $display("");
        $display("============================================");

        if(errors == 0)
        begin
            $display("       ALL CHECKS PASSED");
        end
        else
        begin
            $display("       TEST FAILED");
            $display("       Total Errors = %0d", errors);
        end

        $display("============================================");
        $display("");

        #20;

        $finish;

    end

endmodule

// module fifo_tb;
// reg rst, clk, en, push_in, pop_in;
// reg [7:0] din;
// wire [7:0] dout;
// wire empty, full, overrun, underrun;
// reg [3:0] threshold;
// wire thre_trigger;
 
// initial begin
// rst = 0;
// clk = 0;
// en = 0;
// din = 0;
// end
 
 
 
 
// fifo_top dut_fifo (rst, clk, en, push_in, pop_in, din, dout,empty, full, overrun, underrun,threshold,thre_trigger );
 
// always #5 clk = ~clk;
 
// initial begin
//     $dumpfile("fifo_top.vcd");
//     $dumpvars(0, fifo_tb);
// end

// initial begin
// rst = 1'b1;
// repeat(5)@(posedge clk);
 
// for(int i = 0; i<20 ; i++)
// begin
// rst = 1'b0;
// push_in = 1'b1;
// din = $urandom();
// pop_in = 1'b0;
// en = 1'b1;
// threshold = 4'ha;
// @(posedge clk);
// end
// ///////////////////read
// for(int i = 0; i<20 ; i++)
// begin
// rst = 1'b0;
// push_in = 1'b0;
// din = 0;
// pop_in = 1'b1;
// en = 1'b1;
// threshold = 4'ha;
// @(posedge clk);
// end
 
// $finish;

// end
// endmodule

fifo_top.vcd
$date
	Thu Aug 27 23:37:39 2026
$end
$version
	Icarus Verilog
$end
$timescale
	1ps
$end
$scope module fifo_tb $end
$var wire 1 ! underrun $end
$var wire 1 " th_trigger $end
$var wire 1 # overrun $end
$var wire 1 $ full $end
$var wire 1 % empty $end
$var wire 8 & dout [7:0] $end
$var reg 1 ' clk $end
$var reg 8 ( din [7:0] $end
$var reg 1 ) en $end
$var reg 8 * expected [7:0] $end
$var reg 1 + pop_in $end
$var reg 1 , push_in $end
$var reg 1 - rst $end
$var reg 4 . threshold [3:0] $end
$var integer 32 / errors [31:0] $end
$var integer 32 0 i [31:0] $end
$scope module dut_fifo $end
$var wire 1 ' clk $end
$var wire 8 1 din [7:0] $end
$var wire 8 2 dout [7:0] $end
$var wire 1 % empty $end
$var wire 1 ) en $end
$var wire 1 $ full $end
$var wire 1 # overrun $end
$var wire 1 3 pop $end
$var wire 1 + pop_in $end
$var wire 1 4 push $end
$var wire 1 , push_in $end
$var wire 1 - rst $end
$var wire 1 " th_trigger $end
$var wire 4 5 threshold [3:0] $end
$var wire 1 ! underrun $end
$var reg 1 6 empty_t $end
$var reg 1 7 full_t $end
$var reg 1 8 overrun_t $end
$var reg 1 9 thre_t $end
$var reg 1 : underrun_t $end
$var reg 4 ; waddr [3:0] $end
$scope begin $ivl_for_loop0 $end
$var integer 32 < i [31:0] $end
$upscope $end
$scope begin $ivl_for_loop1 $end
$var integer 32 = i [31:0] $end
$upscope $end
$upscope $end
$upscope $end
$enddefinitions $end
#0
$dumpvars
b0 =
b0 <
b0 ;
0:
09
08
07
06
b1010 5
04
03
bx 2
b0 1
bx 0
b0 /
b1010 .
1-
0,
0+
bx *
0)
b0 (
0'
bx &
0%
0$
0#
0"
0!
$end
#5000
1'
#10000
0'
#15000
1'
#20000
0'
#25000
1)
0-
1'
#30000
0'
#35000
14
1,
b10000 (
b10000 1
b0 0
1'
#40000
0'
#45000
b10000 &
b10000 2
1'
#46000
b10001 (
b10001 1
b1 0
#50000
0'
#55000
b10001 &
b10001 2
1'
#56000
b10010 (
b10010 1
b10 0
#60000
0'
#65000
b10010 &
b10010 2
1'
#66000
b10011 (
b10011 1
b11 0
#70000
0'
#75000
b10011 &
b10011 2
1'
#76000
b10100 (
b10100 1
b100 0
#80000
0'
#85000
b10100 &
b10100 2
1'
#86000
04
0,
b101 0
#90000
0'
#95000
13
1+
b10000 *
b0 0
1'
#100000
0'
#105000
03
bx &
bx 2
b1 ;
1%
16
b1110 <
1'
#106000
b10001 *
b1 0
b1 /
#110000
0'
#115000
1!
1:
1'
#116000
b10010 *
b10 0
b10 /
#120000
0'
#125000
1'
#126000
b10011 *
b11 0
b11 /
#130000
0'
#135000
1'
#136000
b10100 *
b100 0
b100 /
#140000
0'
#145000
1'
#146000
14
1,
b10100000 (
b10100000 1
0+
b0 0
b101 /
#150000
0'
#155000
0%
06
0!
0:
1'
#156000
b10100001 (
b10100001 1
b1 0
#160000
0'
#165000
b0 ;
1'
#166000
b10100010 (
b10100010 1
b10 0
#170000
0'
#175000
b10100010 &
b10100010 2
1'
#176000
b10100011 (
b10100011 1
b11 0
#180000
0'
#185000
b10100011 &
b10100011 2
1'
#186000
b10100100 (
b10100100 1
b100 0
#190000
0'
#195000
b10100100 &
b10100100 2
1'
#196000
b10100101 (
b10100101 1
b101 0
#200000
0'
#205000
b10100101 &
b10100101 2
1'
#206000
b10100110 (
b10100110 1
b110 0
#210000
0'
#215000
b10100110 &
b10100110 2
1'
#216000
b10100111 (
b10100111 1
b111 0
#220000
0'
#225000
b10100111 &
b10100111 2
1'
#226000
b10101000 (
b10101000 1
b1000 0
#230000
0'
#235000
b10101000 &
b10101000 2
1'
#236000
b10101001 (
b10101001 1
b1001 0
#240000
0'
#245000
b10101001 &
b10101001 2
1'
#246000
b10101010 (
b10101010 1
b1010 0
#250000
0'
#255000
b10101010 &
b10101010 2
1'
#256000
b10101011 (
b10101011 1
b1011 0
#260000
0'
#265000
b10101011 &
b10101011 2
1'
#266000
b10101100 (
b10101100 1
b1100 0
#270000
0'
#275000
b10101100 &
b10101100 2
1'
#276000
b10101101 (
b10101101 1
b1101 0
#280000
0'
#285000
b10101101 &
b10101101 2
1'
#286000
b10101110 (
b10101110 1
b1110 0
#290000
0'
#295000
b10101110 &
b10101110 2
1'
#296000
b10101111 (
b10101111 1
b1111 0
#300000
0'
#305000
b10101111 &
b10101111 2
1'
#306000
04
0,
b10000 0
#310000
0'
#315000
14
1,
b11111111 (
b11111111 1
b110 /
1'
#320000
0'
#325000
b11111111 &
b11111111 2
1'
#326000
13
04
b0 0
1+
0,
b111 /
#330000
0'
#335000
03
b10100001 &
b10100001 2
1%
16
b1 ;
b1110 <
1'
#336000
b1 0
#340000
0'
#345000
1!
1:
1'
#346000
b10 0
#350000
0'
#355000
1'
#356000
b11 0
#360000
0'
#365000
1'
#366000
b100 0
#370000
0'
#375000
1'
#376000
b101 0
#380000
0'
#385000
1'
#386000
b110 0
#390000
0'
#395000
1'
#396000
b111 0
#400000
0'
#405000
1'
#406000
b1000 0
#410000
0'
#415000
1'
#416000
b1001 0
#420000
0'
#425000
1'
#426000
b1010 0
#430000
0'
#435000
1'
#436000
b1011 0
#440000
0'
#445000
1'
#446000
b1100 0
#450000
0'
#455000
1'
#456000
b1101 0
#460000
0'
#465000
1'
#466000
b1110 0
#470000
0'
#475000
1'
#476000
b1111 0
#480000
0'
#485000
1'
#486000
0+
b10000 0
#490000
0'
#495000
1+
1'
#500000
0'
#505000
1'
#506000
14
1,
b1010000 (
b1010000 1
b0 0
b101 .
b101 5
0+
#510000
0'
#515000
0%
06
0!
0:
1'
#516000
b1010001 (
b1010001 1
b1 0
#520000
0'
#525000
b0 ;
1'
#526000
b1010010 (
b1010010 1
b10 0
#530000
0'
#535000
b1010010 &
b1010010 2
1'
#536000
b1010011 (
b1010011 1
b11 0
#540000
0'
#545000
b1010011 &
b1010011 2
1'
#546000
b1010100 (
b1010100 1
b100 0
#550000
0'
#555000
b1010100 &
b1010100 2
1'
#556000
b1010101 (
b1010101 1
b101 0
#560000
0'
#565000
b1010101 &
b1010101 2
1'
#566000
04
0,
b110 0
