full_subtractor.v
// this is the rtl code for full subtractor


module full_subtractor (a,b,c,d,bor);

    input a,b,c;
    output d,bor;
    reg [1:0] temp;

    always @ (a or b or c)
        begin
        temp = a-b-c;
        end

    assign d = temp[0];
    assign bor = temp[1];

endmodule

full_subtractor_tb.v
// This is the testbench for full subtractor that generates the VCD file

module tb_full_subtractor;

    reg a;
    reg b;
    reg c;     // borrow in
    wire d;    // difference
    wire bor;  // borrow out

    full_subtractor DUT (
        .a(a),
        .b(b),
        .c(c),
        .d(d),
        .bor(bor)
    );  // <-- missing semicolon fixed

    // VCD dump
    initial begin
        $dumpfile("full_subtractor.vcd");
        $dumpvars(0, tb_full_subtractor); // corrected dumpvars
    end

    // Monitor output continuously
    initial begin
        $monitor("Time=%0t  A=%b  B=%b  C=%b | D=%b  BOR=%b", 
                  $time, a, b, c, d, bor);
    end

    // Apply input combinations
    initial begin
        a = 0; b = 0; c = 0; #10;
        a = 0; b = 1; c = 0; #10;
        a = 1; b = 0; c = 0; #10;
        a = 1; b = 1; c = 0; #10;

        a = 0; b = 0; c = 1; #10;
        a = 0; b = 1; c = 1; #10;
        a = 1; b = 0; c = 1; #10;
        a = 1; b = 1; c = 1; #10;

        $finish;
    end

endmodule

full_subtractor.vcd
$date
	Fri Dec 12 20:37:36 2025
$end
$version
	Icarus Verilog
$end
$timescale
	1s
$end
$scope module tb_full_subtractor $end
$var wire 1 ! d $end
$var wire 1 " bor $end
$var reg 1 # a $end
$var reg 1 $ b $end
$var reg 1 % c $end
$scope module DUT $end
$var wire 1 # a $end
$var wire 1 $ b $end
$var wire 1 % c $end
$var wire 1 ! d $end
$var wire 1 " bor $end
$var reg 2 & temp [1:0] $end
$upscope $end
$upscope $end
$enddefinitions $end
#0
$dumpvars
b0 &
0%
0$
0#
0"
0!
$end
#10
1!
1"
b11 &
1$
#20
0"
b1 &
0$
1#
#30
0!
b0 &
1$
#40
1!
1"
b11 &
1%
0$
0#
#50
0!
b10 &
1$
#60
0"
b0 &
0$
1#
#70
1!
1"
b11 &
1$
