Gray_Counter.v
module Gray_Counter(clk, reset, data_in, load_en, out);

    input clk, reset;
    input load_en;
    input [3:0] data_in;
    
    output reg [3:0] out;
    reg q0, q1, q2;
    reg [3:0] count;

    always @(posedge clk) begin
        if (reset) begin
            count <= 4'b0;
            {q2,q1,q0} <= 3'b000;
            out <= 4'b0;
        end
        
        else if (load_en) begin
            count <= data_in;
            {q2, q1, q0} <= {data_in[2], data_in[1], data_in[0]};
            out <= {data_in[3], data_in[2], data_in[1], data_in[0]};
        end
        else begin
            count <= count + 1'b1;
            q2 <= count[3] ^ count[2];
            q1 <= count[2] ^ count[1];
            q0 <= count[1] ^ count[0];
            out <= {count[3],q2,q1,q0};

        end

    end
endmodule

Gray_Counter_tb.v
module tb_Gray_Counter();

    reg clk, reset, load_en;
    reg [3:0] data_in;
    wire [3:0] out;

    Gray_Counter DUT (
        .clk(clk),
        .reset(reset),
        .data_in(data_in),
        .load_en(load_en),
        .out(out)
    );

    // Clock generation: 10ns period
    initial begin
        clk = 0;
        forever #5 clk = ~clk;
    end

    // Dumpfile for GTKWave
    initial begin
        $dumpfile("Gray_Counter.vcd");
        $dumpvars(0, tb_Gray_Counter);
    end

    initial begin
        $monitor("Time=%0t | reset=%b load_en=%b data_in=%b | out=%b | count(binary)=%d",
            $time, reset, load_en, data_in, out, DUT.count);
    end

    initial begin
        // Start
        reset = 1; load_en = 0; data_in = 0;
        #10 reset = 0;

        // Load custom value
        load_en = 1; data_in = 4'b0000;
        #10 load_en = 0;

        // Normal Gray counting
        #160;

        // Another load
        load_en = 1; data_in = 4'b1001;
        #10 load_en = 0;

        #90;

        $finish;
    end
endmodule

Gray_Counter.vcd
$date
	Sat Dec 27 00:08:32 2025
$end
$version
	Icarus Verilog
$end
$timescale
	1s
$end
$scope module tb_Gray_Counter $end
$var wire 4 ! out [3:0] $end
$var reg 1 " clk $end
$var reg 4 # data_in [3:0] $end
$var reg 1 $ load_en $end
$var reg 1 % reset $end
$scope module DUT $end
$var wire 1 " clk $end
$var wire 4 & data_in [3:0] $end
$var wire 1 $ load_en $end
$var wire 1 % reset $end
$var reg 4 ' count [3:0] $end
$var reg 4 ( out [3:0] $end
$var reg 1 ) q0 $end
$var reg 1 * q1 $end
$var reg 1 + q2 $end
$upscope $end
$upscope $end
$enddefinitions $end
#0
$dumpvars
x+
x*
x)
bx (
bx '
b0 &
1%
0$
b0 #
0"
bx !
$end
#5
b0 !
b0 (
0+
0*
0)
b0 '
1"
#10
0"
1$
0%
#15
1"
#20
0"
0$
#25
b1 '
1"
#30
0"
#35
1)
b10 '
1"
#40
0"
#45
b1 !
b1 (
1*
b11 '
1"
#50
0"
#55
b11 !
b11 (
0)
b100 '
1"
#60
0"
#65
b10 !
b10 (
1+
b101 '
1"
#70
0"
#75
b110 !
b110 (
1)
b110 '
1"
#80
0"
#85
b111 !
b111 (
0*
b111 '
1"
#90
0"
#95
b101 !
b101 (
0)
b1000 '
1"
#100
0"
#105
b1100 !
b1100 (
b1001 '
1"
#110
0"
#115
1)
b1010 '
1"
#120
0"
#125
b1101 !
b1101 (
1*
b1011 '
1"
#130
0"
#135
b1111 !
b1111 (
0)
b1100 '
1"
#140
0"
#145
b1110 !
b1110 (
0+
b1101 '
1"
#150
0"
#155
b1010 !
b1010 (
1)
b1110 '
1"
#160
0"
#165
b1011 !
b1011 (
0*
b1111 '
1"
#170
0"
#175
b1001 !
b1001 (
0)
b0 '
1"
#180
0"
b1001 #
b1001 &
1$
#185
1)
b1001 '
1"
#190
0"
0$
#195
1+
b1010 '
1"
#200
0"
#205
b1101 !
b1101 (
1*
b1011 '
1"
#210
0"
#215
b1111 !
b1111 (
0)
b1100 '
1"
#220
0"
#225
b1110 !
b1110 (
0+
b1101 '
1"
#230
0"
#235
b1010 !
b1010 (
1)
b1110 '
1"
#240
0"
#245
b1011 !
b1011 (
0*
b1111 '
1"
#250
0"
#255
b1001 !
b1001 (
0)
b0 '
1"
#260
0"
#265
b0 !
b0 (
b1 '
1"
#270
0"
#275
1)
b10 '
1"
