Johnson_Counter.v
module Johnson_Counter(reset_n,clk,q_out);

    input reset_n,clk;
    output reg [3:0] q_out;

    always @(posedge clk or negedge reset_n) begin
        if(~reset_n)
            q_out <= 4'b0000;
        else
            q_out <= {{q_out[2:0]},{~q_out[3]}};
    end
endmodule

Johnson_Counter_tb.v
module tb_Johnson_Counter;
    reg reset_n,clk;
    wire [3:0] q_out;

    Johnson_Counter DUT (
        .reset_n(reset_n),
        .clk(clk),
        .q_out(q_out)
    );

    initial begin
        clk = 0;
        forever #5 clk =~clk;
    end

    initial begin
        $dumpfile("Johnson_Counter.vcd");
        $dumpvars(0,tb_Johnson_Counter);
    end

    initial begin
        $monitor("Time=%0t | reset_n=%b  clk=%b | q_out=%b",
            $time, reset_n,clk,q_out);
    end
    
    initial begin
        // Apply reset
        reset_n = 0;
        #12;

        // Release reset
        reset_n = 1;

        // Let it run for some cycles
        #100;

        // Apply reset again
        reset_n = 0;
        #10;

        // Release reset again
        reset_n = 1;
        #50;

        $finish;
    end

endmodule

Johnson_Counter.vcd
$date
	Tue Jan 13 12:24:44 2026
$end
$version
	Icarus Verilog
$end
$timescale
	1s
$end
$scope module tb_Johnson_Counter $end
$var wire 4 ! q_out [3:0] $end
$var reg 1 " clk $end
$var reg 1 # reset_n $end
$scope module DUT $end
$var wire 1 " clk $end
$var wire 1 # reset_n $end
$var reg 4 $ q_out [3:0] $end
$upscope $end
$upscope $end
$enddefinitions $end
#0
$dumpvars
b0 $
0#
0"
b0 !
$end
#5
1"
#10
0"
#12
1#
#15
b1 !
b1 $
1"
#20
0"
#25
b11 !
b11 $
1"
#30
0"
#35
b111 !
b111 $
1"
#40
0"
#45
b1111 !
b1111 $
1"
#50
0"
#55
b1110 !
b1110 $
1"
#60
0"
#65
b1100 !
b1100 $
1"
#70
0"
#75
b1000 !
b1000 $
1"
#80
0"
#85
b0 !
b0 $
1"
#90
0"
#95
b1 !
b1 $
1"
#100
0"
#105
b11 !
b11 $
1"
#110
0"
#112
b0 !
b0 $
0#
#115
1"
#120
0"
#122
1#
#125
b1 !
b1 $
1"
#130
0"
#135
b11 !
b11 $
1"
#140
0"
#145
b111 !
b111 $
1"
#150
0"
#155
b1111 !
b1111 $
1"
#160
0"
#165
b1110 !
b1110 $
1"
