logic_with_sharing.v
module logic_with_sharing(a, b, c, d, e, f, s1, s2, x, y);

    input a, b, c, d, e, f, s1, s2;
    output x, y;
    reg x, y; 
    reg temp1, temp2, temp3, temp4;

    always @(a or b or c or d or s1)
    begin
        if (s1)
        begin
            temp1 = a;
            temp2 = b;
        end
        else
        begin
            temp1 = c;
            temp2 = d; 
        end
    end

    always @(e or f or a or b or s2)
    begin
        if (s2) begin
            temp3 = e;
            temp4 = f;
        end
        else begin
            temp3 = a;
            temp4 = b;
        end
    end

    always @(temp1 or temp2 or temp3 or temp4) begin
        x = temp1 + temp2;
        y = temp3 + temp4;
    end

endmodule

logic_with_sharing_tb.v
module tb_logic_with_sharing();

    reg a, b, c, d, e, f, s1, s2;
    wire x, y;

    logic_with_sharing DUT (
        .a(a),
        .b(b),
        .c(c),
        .d(d),
        .e(e),
        .f(f),
        .x(x),
        .y(y)
    );

    initial begin
        $dumpfile("logic_with_sharing.vcd");
        $dumpvars(0, tb_logic_with_sharing);
    end

    initial begin
        $monitor("Time=%0t |  s1 = %d s2 = %d a = %d b = %d c = %d d = %d e = %d f = %d  |  x = %d y = %d",
                 $time,s1, s2, a, b, c, d, e, f, x, y);
    end


    initial begin
        #10 s1 =  0; s2 =  1; a =  0; b =  0; c =  0; d =  1; e =  1; f =  1;
        #10 s1 =  0; s2 =  1; a =  1; b =  0; c =  0; d =  0; e =  1; f =  0;
        #10 s1 =  0; s2 =  1; a =  0; b =  1; c =  0; d =  1; e =  0; f =  1;
        #10 s1 =  0; s2 =  1; a =  1; b =  1; c =  0; d =  0; e =  0; f =  0;
        #10 s1 =  1; s2 =  1; a =  0; b =  0; c =  1; d =  1; e =  0; f =  0;
        #10 s1 =  1; s2 =  1; a =  1; b =  0; c =  1; d =  0; e =  0; f =  1;
        #10 s1 =  1; s2 =  1; a =  0; b =  1; c =  1; d =  1; e =  0; f =  1;
        #10 s1 =  0; s2 =  0; a =  1; b =  1; c =  1; d =  0; e =  0; f =  1;
        #10 s1 =  0; s2 =  0; a =  0; b =  0; c =  0; d =  1; e =  1; f =  1;
        #10 s1 =  0; s2 =  0; a =  1; b =  0; c =  0; d =  0; e =  1; f =  1;

        #10 $finish;

    end

endmodule

logic_with_sharing.vcd
$date
	Tue Dec 16 22:13:18 2025
$end
$version
	Icarus Verilog
$end
$timescale
	1s
$end
$scope module tb_logic_with_sharing $end
$var wire 1 ! y $end
$var wire 1 " x $end
$var reg 1 # a $end
$var reg 1 $ b $end
$var reg 1 % c $end
$var reg 1 & d $end
$var reg 1 ' e $end
$var reg 1 ( f $end
$var reg 1 ) s1 $end
$var reg 1 * s2 $end
$scope module DUT $end
$var wire 1 # a $end
$var wire 1 $ b $end
$var wire 1 % c $end
$var wire 1 & d $end
$var wire 1 ' e $end
$var wire 1 ( f $end
$var wire 1 + s1 $end
$var wire 1 , s2 $end
$var reg 1 - temp1 $end
$var reg 1 . temp2 $end
$var reg 1 / temp3 $end
$var reg 1 0 temp4 $end
$var reg 1 " x $end
$var reg 1 ! y $end
$upscope $end
$upscope $end
$enddefinitions $end
#0
$dumpvars
x0
x/
x.
x-
z,
z+
x*
x)
x(
x'
x&
x%
x$
x#
x"
x!
$end
#10
0!
1"
00
0/
1.
0-
1(
1'
1&
0%
0$
0#
1*
0)
#20
1!
0"
1/
0.
0(
0&
1#
#30
1"
10
0/
1.
1(
0'
1&
1$
0#
#40
0!
0"
1/
0.
0(
0&
1#
#50
00
0/
1.
1-
1&
1%
0$
0#
1)
#60
1!
1"
1/
0.
1(
0&
1#
#70
0"
10
0/
1.
1&
1$
0#
#80
0!
1"
1/
0.
0&
1#
0*
0)
#90
00
0/
1.
0-
1'
1&
0%
0$
0#
#100
1!
0"
1/
0.
0&
1#
