mux_2to1.v
module mux_2to1 (A,B,S,Y);
    input A,B,S;
    output Y;
    
    assign Y = (S) ? B:A;
endmodule

mux_2to1_tb.v
module tb_mux_2to1;

    reg A, B, S;
    wire Y;

    // Instantiate the DUT
    mux_2to1 DUT (
        .A(A),
        .B(B),
        .S(S),
        .Y(Y)
    );

    // VCD file generation
    initial begin
        $dumpfile("mux_2to1.vcd");
        $dumpvars(0, tb_mux_2to1);
    end

    // Monitor output whenever signals change
    initial begin
        $monitor("Time=%0t  A=%b  B=%b  S=%b  |  Y=%b",
                 $time, A, B, S, Y);
    end

    // Apply test vectors
    initial begin
        A = 0; B = 0; S = 0; #10;   // Expect Y = A = 0
        A = 0; B = 1; S = 0; #10;   // Expect Y = A = 0
        A = 1; B = 0; S = 0; #10;   // Expect Y = A = 1
        A = 1; B = 1; S = 0; #10;   // Expect Y = A = 1

        A = 0; B = 0; S = 1; #10;   // Expect Y = B = 0
        A = 0; B = 1; S = 1; #10;   // Expect Y = B = 1
        A = 1; B = 0; S = 1; #10;   // Expect Y = B = 0
        A = 1; B = 1; S = 1; #10;   // Expect Y = B = 1

        $finish;
    end

endmodule

mux_2to1.vcd
$date
	Sat Dec 13 12:18:46 2025
$end
$version
	Icarus Verilog
$end
$timescale
	1s
$end
$scope module tb_mux_2to1 $end
$var wire 1 ! Y $end
$var reg 1 " A $end
$var reg 1 # B $end
$var reg 1 $ S $end
$scope module DUT $end
$var wire 1 " A $end
$var wire 1 # B $end
$var wire 1 $ S $end
$var wire 1 ! Y $end
$upscope $end
$upscope $end
$enddefinitions $end
#0
$dumpvars
0$
0#
0"
0!
$end
#10
1#
#20
1!
0#
1"
#30
1#
#40
0!
1$
0#
0"
#50
1!
1#
#60
0!
0#
1"
#70
1!
1#
