parameterizedCounter.v
module parameterizedCounter (data_in, load_en, clk, reset_n, count_out);
    parameter N= 8;
    input reset_n, clk, load_en;
    input [N-1:0] data_in;
    output reg [N-1:0] count_out;
    always @(posedge clk) begin
        if(~reset_n)
        count_out<=0;
        else if(load_en)
        count_out<=data_in;
        else
        count_out<=count_out+1'b1;
    end
endmodule

parameterizedCounter_tb.v
module parameterizedCounter_tb ();
    parameter N = 8;
    reg clk, load_en, reset_n;
    reg [N-1:0] data_in;
    wire [N-1:0] count_out;

    parameterizedCounter DUT(
        .clk(clk),
        .data_in(data_in),
        .load_en(load_en),
        .reset_n(reset_n),
        .count_out(count_out)
    );

    // clock: 10 time-unit period
    initial begin
        clk = 0;
        forever #5 clk = ~clk;
    end

    initial begin
        $dumpfile("parameterizedCounter.vcd");
        $dumpvars(0, parameterizedCounter_tb);
    end

    initial begin
        $monitor("Time=%0t | reset_n=%b load_en=%b data_in=%b | count_out=%b",
                 $time, reset_n, load_en, data_in, count_out);
    end

    initial begin
        // -----------------------
        // Init
        // -----------------------
        reset_n = 1'b0;
        load_en = 1'b0;
        data_in = {N{1'b0}};

        // Hold reset for 2 clock cycles
        @(posedge clk);
        @(posedge clk);
        reset_n = 1'b1;

        // -----------------------
        // Test 1: Normal counting
        // -----------------------
        repeat(6) @(posedge clk);

        // -----------------------
        // Test 2: Load zero
        // -----------------------
        load_en = 1'b1;
        data_in = 8'b0000_0000;
        @(posedge clk);          // load happens here
        load_en = 1'b0;

        repeat(4) @(posedge clk);

        // -----------------------
        // Test 3: Load 0x38
        // -----------------------
        load_en = 1'b1;
        data_in = 8'b0011_1000;  // 0x38
        @(posedge clk);          // load happens here
        load_en = 1'b0;

        repeat(5) @(posedge clk);

        // -----------------------
        // Test 4 (NEW): Load max value 0xFF and check overflow wrap
        // -----------------------
        load_en = 1'b1;
        data_in = 8'b1111_1111;  // 0xFF
        @(posedge clk);          // load happens here
        load_en = 1'b0;

        // after increment -> should wrap (FF + 1 = 00)
        repeat(3) @(posedge clk);

        // -----------------------
        // Test 5 (NEW): Reset in middle of counting
        // -----------------------
        reset_n = 1'b0;
        @(posedge clk);
        @(posedge clk);
        reset_n = 1'b1;

        repeat(4) @(posedge clk);

        $finish;
    end

endmodule

parameterizedCounter.vcd
$date
	Thu Jan 15 13:36:01 2026
$end
$version
	Icarus Verilog
$end
$timescale
	1s
$end
$scope module parameterizedCounter_tb $end
$var wire 8 ! count_out [7:0] $end
$var reg 1 " clk $end
$var reg 8 # data_in [7:0] $end
$var reg 1 $ load_en $end
$var reg 1 % reset_n $end
$scope module DUT $end
$var wire 1 " clk $end
$var wire 8 & data_in [7:0] $end
$var wire 1 $ load_en $end
$var wire 1 % reset_n $end
$var reg 8 ' count_out [7:0] $end
$upscope $end
$upscope $end
$enddefinitions $end
#0
$dumpvars
bx '
b0 &
0%
0$
b0 #
0"
bx !
$end
#5
b0 !
b0 '
1"
#10
0"
#15
1%
1"
#20
0"
#25
b1 !
b1 '
1"
#30
0"
#35
b10 !
b10 '
1"
#40
0"
#45
b11 !
b11 '
1"
#50
0"
#55
b100 !
b100 '
1"
#60
0"
#65
b101 !
b101 '
1"
#70
0"
#75
b110 !
b110 '
1$
1"
#80
0"
#85
b111 !
b111 '
0$
1"
#90
0"
#95
b1000 !
b1000 '
1"
#100
0"
#105
b1001 !
b1001 '
1"
#110
0"
#115
b1010 !
b1010 '
1"
#120
0"
#125
b111000 !
b111000 '
b111000 #
b111000 &
1$
1"
#130
0"
#135
0$
1"
#140
0"
#145
b111001 !
b111001 '
1"
#150
0"
#155
b111010 !
b111010 '
1"
#160
0"
#165
b111011 !
b111011 '
1"
#170
0"
#175
b111100 !
b111100 '
1"
#180
0"
#185
b11111111 !
b11111111 '
b11111111 #
b11111111 &
1$
1"
#190
0"
#195
0$
1"
#200
0"
#205
b0 !
b0 '
1"
#210
0"
#215
b1 !
b1 '
1"
#220
0"
#225
b0 !
b0 '
0%
1"
#230
0"
#235
1"
#240
0"
#245
b1 !
b1 '
1%
1"
#250
0"
#255
b10 !
b10 '
1"
#260
0"
#265
b11 !
b11 '
1"
#270
0"
#275
b100 !
b100 '
1"
#280
0"
#285
b101 !
b101 '
1"
