ring_counter.v
module ring_counter(clk, set_in, count_out);
    input clk, set_in;
    output reg [3:0] count_out;
    always @(posedge clk) begin
        if (set_in)
            count_out <= 4'b1000;
        else begin
            count_out <= (count_out<<1);
            count_out[0] <= count_out[3];
        end
    end
endmodule

ring_counter_tb.v
module tb_ring_counter();

    reg clk, set_in;
    wire [3:0] count_out;

    ring_counter DUT (
        .clk(clk),
        .set_in(set_in),
        .count_out(count_out)
    );

    initial begin
        $dumpfile("ring_counter.vcd");
        $dumpvars(0,tb_ring_counter);
    end

    initial begin
        clk = 0;
        forever #5 clk = ~clk;
    end


    initial begin
        $monitor("Time=%0t  |  set=%d  out=%d",
            $time, set_in, count_out);
    end

    initial begin
        set_in = 1; #10;
        set_in = 0; #50;
        set_in = 1; #10;
        set_in = 0; #40;
        $finish;
    end   

endmodule

ring_counter.vcd
$date
	Wed Dec 31 19:18:09 2025
$end
$version
	Icarus Verilog
$end
$timescale
	1s
$end
$scope module tb_ring_counter $end
$var wire 4 ! count_out [3:0] $end
$var reg 1 " clk $end
$var reg 1 # set_in $end
$scope module DUT $end
$var wire 1 " clk $end
$var wire 1 # set_in $end
$var reg 4 $ count_out [3:0] $end
$upscope $end
$upscope $end
$enddefinitions $end
#0
$dumpvars
bx $
1#
0"
bx !
$end
#5
b1000 !
b1000 $
1"
#10
0"
0#
#15
b1 !
b1 $
1"
#20
0"
#25
b10 !
b10 $
1"
#30
0"
#35
b100 !
b100 $
1"
#40
0"
#45
b1000 !
b1000 $
1"
#50
0"
#55
b1 !
b1 $
1"
#60
0"
1#
#65
b1000 !
b1000 $
1"
#70
0"
0#
#75
b1 !
b1 $
1"
#80
0"
#85
b10 !
b10 $
1"
#90
0"
#95
b100 !
b100 $
1"
#100
0"
#105
b1000 !
b1000 $
1"
