seq_and_comb.v
//==========================================================
// Sequential + Combinational Example
//==========================================================

module seq_and_comb (
    input        clk,        // clock
    input        data_in,    // input to D-FF
    output reg   q_out,      // sequential output
    input        a_in,       // input A for MUX
    input        b_in,       // input B for MUX
    input        sel_in,     // select line
    output reg   y_out       // MUX output
);

    // ----------------------------
    // Sequential Logic (D Flip-Flop)
    // ----------------------------
    always @(posedge clk)
    begin
        q_out <= data_in;   // non-blocking assignment
    end

    // ----------------------------
    // Combinational Logic (2:1 MUX)
    // ----------------------------
    always @ (a_in or b_in or sel_in)
    begin
        y_out = sel_in ? a_in : b_in;   // blocking assignment
    end

endmodule

seq_and_comb_tb.v
//==========================================================
// Testbench for seq_and_comb
//==========================================================

module tb_seq_and_comb;

    reg clk;
    reg data_in;
    wire q_out;

    reg a_in, b_in, sel_in;
    wire y_out;

    // Instantiate DUT
    seq_and_comb DUT (
        .clk(clk),
        .data_in(data_in),
        .q_out(q_out),
        .a_in(a_in),
        .b_in(b_in),
        .sel_in(sel_in),
        .y_out(y_out)
    );

    // ----------------------------
    // Clock Generation (10ns period)
    // ----------------------------
    initial begin
        clk = 0;
        forever #5 clk = ~clk;
    end

    // ----------------------------
    // VCD file for waveform
    // ----------------------------
    initial begin
        $dumpfile("seq_and_comb.vcd");
        $dumpvars(0, tb_seq_and_comb);
    end

    // ----------------------------
    // Monitor all changes
    // ----------------------------
    initial begin
        $monitor("Time=%0t | clk=%b  data_in=%b  q_out=%b | sel=%b  a=%b  b=%b  y_out=%b",
                 $time, clk, data_in, q_out, sel_in, a_in, b_in, y_out);
    end

    // ----------------------------
    // Test Stimulus
    // ----------------------------
    initial begin
        // Initial values
        data_in = 0;
        a_in = 0; b_in = 1; sel_in = 0;

        // Sequential & combinational tests
        #10 data_in = 1;
        #10 data_in = 0;

        // MUX tests
        #10 sel_in = 0; a_in = 0; b_in = 1;
        #10 sel_in = 1; a_in = 1; b_in = 0;
        #10 sel_in = 0; a_in = 1; b_in = 0;
        #10 sel_in = 1; a_in = 0; b_in = 1;

        #30 $finish;
    end

endmodule

seq_and_comb.vcd
$date
	Sat Dec 13 21:52:54 2025
$end
$version
	Icarus Verilog
$end
$timescale
	1s
$end
$scope module tb_seq_and_comb $end
$var wire 1 ! y_out $end
$var wire 1 " q_out $end
$var reg 1 # a_in $end
$var reg 1 $ b_in $end
$var reg 1 % clk $end
$var reg 1 & data_in $end
$var reg 1 ' sel_in $end
$scope module DUT $end
$var wire 1 # a_in $end
$var wire 1 $ b_in $end
$var wire 1 % clk $end
$var wire 1 & data_in $end
$var wire 1 ' sel_in $end
$var reg 1 " q_out $end
$var reg 1 ! y_out $end
$upscope $end
$upscope $end
$enddefinitions $end
#0
$dumpvars
0'
0&
0%
1$
0#
x"
1!
$end
#5
0"
1%
#10
0%
1&
#15
1"
1%
#20
0%
0&
#25
0"
1%
#30
0%
#35
1%
#40
0%
0$
1#
1'
#45
1%
#50
0!
0%
0'
#55
1%
#60
0%
1$
0#
1'
