shiftRegister.v
module shiftRegister (data_in,clk,reset_n,data_out);

    input data_in, clk, reset_n;
    output reg data_out;
    reg temp1_out,temp2_out,temp3_out;

    always @(posedge clk or negedge reset_n) begin

        if (~reset_n) begin
            data_out<=1'b0;
            temp1_out<=1'b0;
            temp2_out<=1'b0;
            temp3_out<=1'b0;
        end
        else begin
            temp1_out<=data_in;
            temp2_out<=temp1_out;
            temp3_out<=temp2_out;
            data_out<=temp3_out;
        end
        
    end
    
endmodule

shiftRegister_tb.v
module tb_shiftRegister ();
    reg data_in, clk, reset_n;
    wire data_out;

    shiftRegister DUT (
        .data_in(data_in),
        .clk(clk),
        .reset_n(reset_n),
        .data_out(data_out)
    );
    
    initial begin
        $dumpfile("shiftRegister.vcd");
        $dumpvars(0,tb_shiftRegister);
        $dumpvars(0, DUT);

    end 

    initial begin
        clk=0;
        forever #5 clk=~clk;
    end

    initial begin
        $monitor("Time=%0t  reset_n=%b  data_in=%b  temp1_out=%b  temp2_out=%b  temp3_out=%b  data_out=%b",
        $time, reset_n, data_in, DUT.temp1_out, DUT.temp2_out, DUT.temp3_out, data_out);
    end

    initial begin
        data_in = 0;
        reset_n = 0;

        // hold reset for 2 posedges
        @(posedge clk);
        @(posedge clk);
        reset_n = 1;

        // shift in bits
        data_in = 1; @(posedge clk);
        data_in = 0; @(posedge clk);
        data_in = 1; @(posedge clk);
        data_in = 1; @(posedge clk);
        data_in = 0; @(posedge clk);

        #10 $finish;
    end
endmodule

shiftRegister.vcd
$date
	Thu Jan 15 23:09:29 2026
$end
$version
	Icarus Verilog
$end
$timescale
	1s
$end
$scope module tb_shiftRegister $end
$var wire 1 ! data_out $end
$var reg 1 " clk $end
$var reg 1 # data_in $end
$var reg 1 $ reset_n $end
$scope module DUT $end
$var wire 1 " clk $end
$var wire 1 # data_in $end
$var wire 1 $ reset_n $end
$var reg 1 ! data_out $end
$var reg 1 % temp1_out $end
$var reg 1 & temp2_out $end
$var reg 1 ' temp3_out $end
$upscope $end
$upscope $end
$enddefinitions $end
#0
$dumpvars
0'
0&
0%
0$
0#
0"
0!
$end
#5
1"
#10
0"
#15
1%
1#
1$
1"
#20
0"
#25
1&
0%
0#
1"
#30
0"
#35
1'
0&
1%
1#
1"
#40
0"
#45
1!
0'
1&
1"
#50
0"
#55
0!
1'
0%
0#
1"
#60
0"
#65
1!
0&
1"
#70
0"
#75
0'
1"
