uart_top.v
`timescale 1ns/1ps

module uart_top 
#(parameter clk_freq = 1000000,
parameter baud_rate = 9600)
(
	input clk, rst, rx,
    input newd,
    input [7:0] dintx,
    output tx,
    output [7:0] doutrx,
	output donerx, donetx
);

uarttx
#(clk_freq, baud_rate)
utx
(clk,rst,newd,dintx,tx,donetx);

uartrx
#(clk_freq, baud_rate)
rtx
(clk,rst,rx,donerx,doutrx);

endmodule


module uarttx
#(parameter clk_freq = 1000000,
parameter baud_rate = 9600)
(
    input clk, rst,
    input newd,
    input [7:0] tx_data,
    output reg tx,
    output reg donetx
    );

    localparam clkcount = (clk_freq/baud_rate) ;

integer count = 0;
integer counts = 0;

reg uclk = 0;

enum bit[1:0] {idle = 2'b00, start = 2'b01, transfer = 2'b10, done = 2'b11} state;

always @(posedge clk) begin
    if (count < clkcount/2)
        count <= count + 1 ;
    else begin
        count <= 0;
        uclk <= ~uclk;
    end
end

reg [7:0] din;

always @(posedge uclk) begin
    if(rst) begin
        state <= idle;
    end
    else begin
        case(state)
            idle:begin
                counts <=0;
                tx <=1'b1;
                donetx <= 1'b0;

                if(newd) begin
                    state<= transfer;
                    din <= tx_data;
                    tx <=  1'b0;
                end
                else
                state <=idle;
            end
			transfer: begin
				if (counts <= 7) begin
					counts <= counts + 1;
					tx <= din[counts];
					state <= transfer;
				end
				else begin
					counts <= 0;
					tx <= 1'b1;
					state <= idle;
					donetx <= 1'b1;
				end
			end

			default : state<= idle;
		endcase    
	end            
end
endmodule









module uartrx
#(parameter clk_freq = 1000000,
parameter baud_rate = 9600)
(
    input clk, rst,
    input rx,
    output reg done,
    output reg [7:0] rxdata
    );

localparam clkcount = (clk_freq/baud_rate) ;

integer count = 0;
integer counts = 0;

reg uclk = 0;
enum bit[1:0] {idle = 2'b00, start = 2'b01} state;

always @(posedge clk) begin
    if (count < clkcount/2)
        count <= count + 1 ;
    else begin
        count <= 0;
        uclk <= ~uclk;
    end
end

always @(posedge uclk ) begin
	if(rst) begin
		rxdata <= 8'h00;
		counts <= 0;
		done <= 1'b0;
	end
	else begin
		case(state)
		idle:begin
			rxdata <= 8'h00;
			counts <= 0;
			done <= 1'b0;
			if (rx == 1'b0) begin
				state <= start;
			end
			else
				state<= idle;
		end

		start: begin
			if (counts <= 7) begin
				counts <= counts + 1;
				rxdata <= {rx, rxdata[7:1]};
			end
			else begin
				counts <= 0;
				done <= 1'b1;
				state <= idle;
			end
		end
		default : state<= idle;
		endcase
	end
end
endmodule

uart_top_tb.v
`timescale 1ns/1ps

module uart_tb;

    // ============================================================
    // DUT signals
    // ============================================================

    reg clk = 0;
    reg rst = 0;
    reg rx = 1;

    reg [7:0] dintx = 0;
    reg newd = 0;

    wire tx;
    wire [7:0] doutrx;
    wire donetx;
    wire donerx;


    // ============================================================
    // DUT
    // ============================================================

uart_top #(1000000, 9600) dut
(
    clk,
    rst,
    rx,
    newd,
    dintx,
    tx,
    doutrx,
    donerx,
    donetx
);


    // ============================================================
    // 100 MHz? NO
    // 1 MHz clock
    // Period = 10 ns
    // ============================================================

    always #5 clk = ~clk;


    // ============================================================
    // Test variables
    // ============================================================

    reg [7:0] tx_data;
    reg [7:0] rx_data;

    integer i;
    integer j;


    // ============================================================
    // VCD generation
    // ============================================================

    initial begin
        $dumpfile("uart_top.vcd");
        $dumpvars(0, uart_tb);
    end


    // ============================================================
    // MAIN TEST
    // ============================================================

    initial begin

        // --------------------------------------------------------
        // Initial values
        // --------------------------------------------------------

        rst    = 1;
        rx     = 1;
        newd   = 0;
        dintx  = 8'h00;

        tx_data = 8'h00;
        rx_data = 8'h00;


        // --------------------------------------------------------
        // Reset
        // --------------------------------------------------------

        $display("");
        $display("======================================");
        $display("       UART SIMULATION START");
        $display("======================================");
        $display("");

        repeat(5) @(posedge clk);

        rst = 0;

        repeat(2) @(posedge dut.utx.uclk);


        // ========================================================
        // TX TEST
        // ========================================================

        $display("======================================");
        $display("             TX TEST");
        $display("======================================");

        for(i = 0; i < 5; i = i + 1)
        begin

            // Generate test byte
            dintx = $urandom_range(0,255);

            tx_data = dintx;

            $display("");
            $display("TX Test %0d", i+1);
            $display("Transmitting = %h (%b)",
                     tx_data,
                     tx_data);


            // Start transmission
            newd = 1;

            // Wait until START bit appears
            wait(tx == 0);

            // Stop new-data request
            newd = 0;


            // ----------------------------------------------------
            // Capture 8 transmitted data bits
            // ----------------------------------------------------

            @(posedge dut.utx.uclk);

            for(j = 0; j < 8; j = j + 1)
            begin
                @(posedge dut.utx.uclk);

                tx_data = {tx, tx_data[7:1]};
            end


            // Wait for transmission complete
            @(posedge donetx);

            $display("TX captured = %b",
                     tx_data);

        end


        // ========================================================
        // RX TEST
        // ========================================================

        $display("");
        $display("======================================");
        $display("             RX TEST");
        $display("======================================");

        for(i = 0; i < 5; i = i + 1)
        begin

            rx_data = $urandom_range(0,255);

            $display("");
            $display("RX Test %0d", i+1);
            $display("Sending to RX = %h (%b)",
                     rx_data,
                     rx_data);


            // ----------------------------------------------------
            // START BIT
            // ----------------------------------------------------

            rx = 1'b0;

            @(posedge dut.rtx.uclk);


            // ----------------------------------------------------
            // DATA BITS
            // LSB first
            // ----------------------------------------------------

            for(j = 0; j < 8; j = j + 1)
            begin

                rx = rx_data[j];

                @(posedge dut.rtx.uclk);

            end


            // ----------------------------------------------------
            // STOP BIT
            // ----------------------------------------------------

            rx = 1'b1;


            // Wait for RX completion
            @(posedge donerx);


            $display("RX received = %h (%b)",
                     doutrx,
                     doutrx);


            // ----------------------------------------------------
            // Compare
            // ----------------------------------------------------

            if(doutrx == rx_data)
            begin
                $display("RX RESULT : PASS");
            end
            else
            begin
                $display("RX RESULT : FAIL");
                $display("Expected  : %h", rx_data);
                $display("Received  : %h", doutrx);
            end

        end


        // ========================================================
        // END SIMULATION
        // ========================================================

        $display("");
        $display("======================================");
        $display("       UART SIMULATION FINISHED");
        $display("======================================");
        $display("");

        #100;

        $finish;

    end

endmodule

uart_top.vcd
$date
	Wed Aug 26 16:59:47 2026
$end
$version
	Icarus Verilog
$end
$timescale
	1ps
$end
$scope module uart_tb $end
$var wire 1 ! tx $end
$var wire 8 " doutrx [7:0] $end
$var wire 1 # donetx $end
$var wire 1 $ donerx $end
$var reg 1 % clk $end
$var reg 8 & dintx [7:0] $end
$var reg 1 ' newd $end
$var reg 1 ( rst $end
$var reg 1 ) rx $end
$var reg 8 * rx_data [7:0] $end
$var reg 8 + tx_data [7:0] $end
$var integer 32 , i [31:0] $end
$var integer 32 - j [31:0] $end
$scope module dut $end
$var wire 1 % clk $end
$var wire 8 . dintx [7:0] $end
$var wire 1 ' newd $end
$var wire 1 ( rst $end
$var wire 1 ) rx $end
$var wire 1 ! tx $end
$var wire 8 / doutrx [7:0] $end
$var wire 1 # donetx $end
$var wire 1 $ donerx $end
$scope module rtx $end
$var wire 1 % clk $end
$var wire 1 ( rst $end
$var wire 1 ) rx $end
$var reg 1 $ done $end
$var reg 8 0 rxdata [7:0] $end
$var reg 1 1 uclk $end
$var integer 32 2 count [31:0] $end
$var integer 32 3 counts [31:0] $end
$var reg 2 4 state [1:0] $end
$upscope $end
$scope module utx $end
$var wire 1 % clk $end
$var wire 1 ' newd $end
$var wire 1 ( rst $end
$var wire 8 5 tx_data [7:0] $end
$var reg 8 6 din [7:0] $end
$var reg 1 # donetx $end
$var reg 1 ! tx $end
$var reg 1 7 uclk $end
$var integer 32 8 count [31:0] $end
$var integer 32 9 counts [31:0] $end
$var reg 2 : state [1:0] $end
$upscope $end
$upscope $end
$upscope $end
$enddefinitions $end
#0
$dumpvars
b0 :
b0 9
b0 8
07
bx 6
b0 5
b0 4
b0 3
b0 2
01
bx 0
bx /
b0 .
bx -
bx ,
b0 +
b0 *
1)
1(
0'
b0 &
0%
x$
x#
bx "
x!
$end
#5000
b1 8
b1 2
1%
#10000
0%
#15000
b10 2
b10 8
1%
#20000
0%
#25000
b11 8
b11 2
1%
#30000
0%
#35000
b100 2
b100 8
1%
#40000
0%
#45000
b101 8
b101 2
0(
1%
#50000
0%
#55000
b110 2
b110 8
1%
#60000
0%
#65000
b111 8
b111 2
1%
#70000
0%
#75000
b1000 2
b1000 8
1%
#80000
0%
#85000
b1001 8
b1001 2
1%
#90000
0%
#95000
b1010 2
b1010 8
1%
#100000
0%
#105000
b1011 8
b1011 2
1%
#110000
0%
#115000
b1100 2
b1100 8
1%
#120000
0%
#125000
b1101 8
b1101 2
1%
#130000
0%
#135000
b1110 2
b1110 8
1%
#140000
0%
#145000
b1111 8
b1111 2
1%
#150000
0%
#155000
b10000 2
b10000 8
1%
#160000
0%
#165000
b10001 8
b10001 2
1%
#170000
0%
#175000
b10010 2
b10010 8
1%
#180000
0%
#185000
b10011 8
b10011 2
1%
#190000
0%
#195000
b10100 2
b10100 8
1%
#200000
0%
#205000
b10101 8
b10101 2
1%
#210000
0%
#215000
b10110 2
b10110 8
1%
#220000
0%
#225000
b10111 8
b10111 2
1%
#230000
0%
#235000
b11000 2
b11000 8
1%
#240000
0%
#245000
b11001 8
b11001 2
1%
#250000
0%
#255000
b11010 2
b11010 8
1%
#260000
0%
#265000
b11011 8
b11011 2
1%
#270000
0%
#275000
b11100 2
b11100 8
1%
#280000
0%
#285000
b11101 8
b11101 2
1%
#290000
0%
#295000
b11110 2
b11110 8
1%
#300000
0%
#305000
b11111 8
b11111 2
1%
#310000
0%
#315000
b100000 2
b100000 8
1%
#320000
0%
#325000
b100001 8
b100001 2
1%
#330000
0%
#335000
b100010 2
b100010 8
1%
#340000
0%
#345000
b100011 8
b100011 2
1%
#350000
0%
#355000
b100100 2
b100100 8
1%
#360000
0%
#365000
b100101 8
b100101 2
1%
#370000
0%
#375000
b100110 2
b100110 8
1%
#380000
0%
#385000
b100111 8
b100111 2
1%
#390000
0%
#395000
b101000 2
b101000 8
1%
#400000
0%
#405000
b101001 8
b101001 2
1%
#410000
0%
#415000
b101010 2
b101010 8
1%
#420000
0%
#425000
b101011 8
b101011 2
1%
#430000
0%
#435000
b101100 2
b101100 8
1%
#440000
0%
#445000
b101101 8
b101101 2
1%
#450000
0%
#455000
b101110 2
b101110 8
1%
#460000
0%
#465000
b101111 8
b101111 2
1%
#470000
0%
#475000
b110000 2
b110000 8
1%
#480000
0%
#485000
b110001 8
b110001 2
1%
#490000
0%
#495000
b110010 2
b110010 8
1%
#500000
0%
#505000
b110011 8
b110011 2
1%
#510000
0%
#515000
b110100 2
b110100 8
1%
#520000
0%
#525000
0#
1!
0$
b0 "
b0 /
b0 0
17
b0 8
11
b0 2
1%
#530000
0%
#535000
b1 2
b1 8
1%
#540000
0%
#545000
b10 8
b10 2
1%
#550000
0%
#555000
b11 2
b11 8
1%
#560000
0%
#565000
b100 8
b100 2
1%
#570000
0%
#575000
b101 2
b101 8
1%
#580000
0%
#585000
b110 8
b110 2
1%
#590000
0%
#595000
b111 2
b111 8
1%
#600000
0%
#605000
b1000 8
b1000 2
1%
#610000
0%
#615000
b1001 2
b1001 8
1%
#620000
0%
#625000
b1010 8
b1010 2
1%
#630000
0%
#635000
b1011 2
b1011 8
1%
#640000
0%
#645000
b1100 8
b1100 2
1%
#650000
0%
#655000
b1101 2
b1101 8
1%
#660000
0%
#665000
b1110 8
b1110 2
1%
#670000
0%
#675000
b1111 2
b1111 8
1%
#680000
0%
#685000
b10000 8
b10000 2
1%
#690000
0%
#695000
b10001 2
b10001 8
1%
#700000
0%
#705000
b10010 8
b10010 2
1%
#710000
0%
#715000
b10011 2
b10011 8
1%
#720000
0%
#725000
b10100 8
b10100 2
1%
#730000
0%
#735000
b10101 2
b10101 8
1%
#740000
0%
#745000
b10110 8
b10110 2
1%
#750000
0%
#755000
b10111 2
b10111 8
1%
#760000
0%
#765000
b11000 8
b11000 2
1%
#770000
0%
#775000
b11001 2
b11001 8
1%
#780000
0%
#785000
b11010 8
b11010 2
1%
#790000
0%
#795000
b11011 2
b11011 8
1%
#800000
0%
#805000
b11100 8
b11100 2
1%
#810000
0%
#815000
b11101 2
b11101 8
1%
#820000
0%
#825000
b11110 8
b11110 2
1%
#830000
0%
#835000
b11111 2
b11111 8
1%
#840000
0%
#845000
b100000 8
b100000 2
1%
#850000
0%
#855000
b100001 2
b100001 8
1%
#860000
0%
#865000
b100010 8
b100010 2
1%
#870000
0%
#875000
b100011 2
b100011 8
1%
#880000
0%
#885000
b100100 8
b100100 2
1%
#890000
0%
#895000
b100101 2
b100101 8
1%
#900000
0%
#905000
b100110 8
b100110 2
1%
#910000
0%
#915000
b100111 2
b100111 8
1%
#920000
0%
#925000
b101000 8
b101000 2
1%
#930000
0%
#935000
b101001 2
b101001 8
1%
#940000
0%
#945000
b101010 8
b101010 2
1%
#950000
0%
#955000
b101011 2
b101011 8
1%
#960000
0%
#965000
b101100 8
b101100 2
1%
#970000
0%
#975000
b101101 2
b101101 8
1%
#980000
0%
#985000
b101110 8
b101110 2
1%
#990000
0%
#995000
b101111 2
b101111 8
1%
#1000000
0%
#1005000
b110000 8
b110000 2
1%
#1010000
0%
#1015000
b110001 2
b110001 8
1%
#1020000
0%
#1025000
b110010 8
b110010 2
1%
#1030000
0%
#1035000
b110011 2
b110011 8
1%
#1040000
0%
#1045000
b110100 8
b110100 2
1%
#1050000
0%
#1055000
01
b0 2
07
b0 8
1%
#1060000
0%
#1065000
b1 8
b1 2
1%
#1070000
0%
#1075000
b10 2
b10 8
1%
#1080000
0%
#1085000
b11 8
b11 2
1%
#1090000
0%
#1095000
b100 2
b100 8
1%
#1100000
0%
#1105000
b101 8
b101 2
1%
#1110000
0%
#1115000
b110 2
b110 8
1%
#1120000
0%
#1125000
b111 8
b111 2
1%
#1130000
0%
#1135000
b1000 2
b1000 8
1%
#1140000
0%
#1145000
b1001 8
b1001 2
1%
#1150000
0%
#1155000
b1010 2
b1010 8
1%
#1160000
0%
#1165000
b1011 8
b1011 2
1%
#1170000
0%
#1175000
b1100 2
b1100 8
1%
#1180000
0%
#1185000
b1101 8
b1101 2
1%
#1190000
0%
#1195000
b1110 2
b1110 8
1%
#1200000
0%
#1205000
b1111 8
b1111 2
1%
#1210000
0%
#1215000
b10000 2
b10000 8
1%
#1220000
0%
#1225000
b10001 8
b10001 2
1%
#1230000
0%
#1235000
b10010 2
b10010 8
1%
#1240000
0%
#1245000
b10011 8
b10011 2
1%
#1250000
0%
#1255000
b10100 2
b10100 8
1%
#1260000
0%
#1265000
b10101 8
b10101 2
1%
#1270000
0%
#1275000
b10110 2
b10110 8
1%
#1280000
0%
#1285000
b10111 8
b10111 2
1%
#1290000
0%
#1295000
b11000 2
b11000 8
1%
#1300000
0%
#1305000
b11001 8
b11001 2
1%
#1310000
0%
#1315000
b11010 2
b11010 8
1%
#1320000
0%
#1325000
b11011 8
b11011 2
1%
#1330000
0%
#1335000
b11100 2
b11100 8
1%
#1340000
0%
#1345000
b11101 8
b11101 2
1%
#1350000
0%
#1355000
b11110 2
b11110 8
1%
#1360000
0%
#1365000
b11111 8
b11111 2
1%
#1370000
0%
#1375000
b100000 2
b100000 8
1%
#1380000
0%
#1385000
b100001 8
b100001 2
1%
#1390000
0%
#1395000
b100010 2
b100010 8
1%
#1400000
0%
#1405000
b100011 8
b100011 2
1%
#1410000
0%
#1415000
b100100 2
b100100 8
1%
#1420000
0%
#1425000
b100101 8
b100101 2
1%
#1430000
0%
#1435000
b100110 2
b100110 8
1%
#1440000
0%
#1445000
b100111 8
b100111 2
1%
#1450000
0%
#1455000
b101000 2
b101000 8
1%
#1460000
0%
#1465000
b101001 8
b101001 2
1%
#1470000
0%
#1475000
b101010 2
b101010 8
1%
#1480000
0%
#1485000
b101011 8
b101011 2
1%
#1490000
0%
#1495000
b101100 2
b101100 8
1%
#1500000
0%
#1505000
b101101 8
b101101 2
1%
#1510000
0%
#1515000
b101110 2
b101110 8
1%
#1520000
0%
#1525000
b101111 8
b101111 2
1%
#1530000
0%
#1535000
b110000 2
b110000 8
1%
#1540000
0%
#1545000
b110001 8
b110001 2
1%
#1550000
0%
#1555000
b110010 2
b110010 8
1%
#1560000
0%
#1565000
b110011 8
b110011 2
1%
#1570000
0%
#1575000
b110100 2
b110100 8
1%
#1580000
0%
#1585000
1'
b10010010 +
b10010010 &
b10010010 .
b10010010 5
b0 ,
17
b0 8
11
b0 2
1%
#1590000
0%
#1595000
b1 2
b1 8
1%
#1600000
0%
#1605000
b10 8
b10 2
1%
#1610000
0%
#1615000
b11 2
b11 8
1%
#1620000
0%
#1625000
b100 8
b100 2
1%
#1630000
0%
#1635000
b101 2
b101 8
1%
#1640000
0%
#1645000
b110 8
b110 2
1%
#1650000
0%
#1655000
b111 2
b111 8
1%
#1660000
0%
#1665000
b1000 8
b1000 2
1%
#1670000
0%
#1675000
b1001 2
b1001 8
1%
#1680000
0%
#1685000
b1010 8
b1010 2
1%
#1690000
0%
#1695000
b1011 2
b1011 8
1%
#1700000
0%
#1705000
b1100 8
b1100 2
1%
#1710000
0%
#1715000
b1101 2
b1101 8
1%
#1720000
0%
#1725000
b1110 8
b1110 2
1%
#1730000
0%
#1735000
b1111 2
b1111 8
1%
#1740000
0%
#1745000
b10000 8
b10000 2
1%
#1750000
0%
#1755000
b10001 2
b10001 8
1%
#1760000
0%
#1765000
b10010 8
b10010 2
1%
#1770000
0%
#1775000
b10011 2
b10011 8
1%
#1780000
0%
#1785000
b10100 8
b10100 2
1%
#1790000
0%
#1795000
b10101 2
b10101 8
1%
#1800000
0%
#1805000
b10110 8
b10110 2
1%
#1810000
0%
#1815000
b10111 2
b10111 8
1%
#1820000
0%
#1825000
b11000 8
b11000 2
1%
#1830000
0%
#1835000
b11001 2
b11001 8
1%
#1840000
0%
#1845000
b11010 8
b11010 2
1%
#1850000
0%
#1855000
b11011 2
b11011 8
1%
#1860000
0%
#1865000
b11100 8
b11100 2
1%
#1870000
0%
#1875000
b11101 2
b11101 8
1%
#1880000
0%
#1885000
b11110 8
b11110 2
1%
#1890000
0%
#1895000
b11111 2
b11111 8
1%
#1900000
0%
#1905000
b100000 8
b100000 2
1%
#1910000
0%
#1915000
b100001 2
b100001 8
1%
#1920000
0%
#1925000
b100010 8
b100010 2
1%
#1930000
0%
#1935000
b100011 2
b100011 8
1%
#1940000
0%
#1945000
b100100 8
b100100 2
1%
#1950000
0%
#1955000
b100101 2
b100101 8
1%
#1960000
0%
#1965000
b100110 8
b100110 2
1%
#1970000
0%
#1975000
b100111 2
b100111 8
1%
#1980000
0%
#1985000
b101000 8
b101000 2
1%
#1990000
0%
#1995000
b101001 2
b101001 8
1%
#2000000
0%
#2005000
b101010 8
b101010 2
1%
#2010000
0%
#2015000
b101011 2
b101011 8
1%
#2020000
0%
#2025000
b101100 8
b101100 2
1%
#2030000
0%
#2035000
b101101 2
b101101 8
1%
#2040000
0%
#2045000
b101110 8
b101110 2
1%
#2050000
0%
#2055000
b101111 2
b101111 8
1%
#2060000
0%
#2065000
b110000 8
b110000 2
1%
#2070000
0%
#2075000
b110001 2
b110001 8
1%
#2080000
0%
#2085000
b110010 8
b110010 2
1%
#2090000
0%
#2095000
b110011 2
b110011 8
1%
#2100000
0%
#2105000
b110100 8
b110100 2
1%
#2110000
0%
#2115000
01
b0 2
07
b0 8
1%
#2120000
0%
#2125000
b1 8
b1 2
1%
#2130000
0%
#2135000
b10 2
b10 8
1%
#2140000
0%
#2145000
b11 8
b11 2
1%
#2150000
0%
#2155000
b100 2
b100 8
1%
#2160000
0%
#2165000
b101 8
b101 2
1%
#2170000
0%
#2175000
b110 2
b110 8
1%
#2180000
0%
#2185000
b111 8
b111 2
1%
#2190000
0%
#2195000
b1000 2
b1000 8
1%
#2200000
0%
#2205000
b1001 8
b1001 2
1%
#2210000
0%
#2215000
b1010 2
b1010 8
1%
#2220000
0%
#2225000
b1011 8
b1011 2
1%
#2230000
0%
#2235000
b1100 2
b1100 8
1%
#2240000
0%
#2245000
b1101 8
b1101 2
1%
#2250000
0%
#2255000
b1110 2
b1110 8
1%
#2260000
0%
#2265000
b1111 8
b1111 2
1%
#2270000
0%
#2275000
b10000 2
b10000 8
1%
#2280000
0%
#2285000
b10001 8
b10001 2
1%
#2290000
0%
#2295000
b10010 2
b10010 8
1%
#2300000
0%
#2305000
b10011 8
b10011 2
1%
#2310000
0%
#2315000
b10100 2
b10100 8
1%
#2320000
0%
#2325000
b10101 8
b10101 2
1%
#2330000
0%
#2335000
b10110 2
b10110 8
1%
#2340000
0%
#2345000
b10111 8
b10111 2
1%
#2350000
0%
#2355000
b11000 2
b11000 8
1%
#2360000
0%
#2365000
b11001 8
b11001 2
1%
#2370000
0%
#2375000
b11010 2
b11010 8
1%
#2380000
0%
#2385000
b11011 8
b11011 2
1%
#2390000
0%
#2395000
b11100 2
b11100 8
1%
#2400000
0%
#2405000
b11101 8
b11101 2
1%
#2410000
0%
#2415000
b11110 2
b11110 8
1%
#2420000
0%
#2425000
b11111 8
b11111 2
1%
#2430000
0%
#2435000
b100000 2
b100000 8
1%
#2440000
0%
#2445000
b100001 8
b100001 2
1%
#2450000
0%
#2455000
b100010 2
b100010 8
1%
#2460000
0%
#2465000
b100011 8
b100011 2
1%
#2470000
0%
#2475000
b100100 2
b100100 8
1%
#2480000
0%
#2485000
b100101 8
b100101 2
1%
#2490000
0%
#2495000
b100110 2
b100110 8
1%
#2500000
0%
#2505000
b100111 8
b100111 2
1%
#2510000
0%
#2515000
b101000 2
b101000 8
1%
#2520000
0%
#2525000
b101001 8
b101001 2
1%
#2530000
0%
#2535000
b101010 2
b101010 8
1%
#2540000
0%
#2545000
b101011 8
b101011 2
1%
#2550000
0%
#2555000
b101100 2
b101100 8
1%
#2560000
0%
#2565000
b101101 8
b101101 2
1%
#2570000
0%
#2575000
b101110 2
b101110 8
1%
#2580000
0%
#2585000
b101111 8
b101111 2
1%
#2590000
0%
#2595000
b110000 2
b110000 8
1%
#2600000
0%
#2605000
b110001 8
b110001 2
1%
#2610000
0%
#2615000
b110010 2
b110010 8
1%
#2620000
0%
#2625000
b110011 8
b110011 2
1%
#2630000
0%
#2635000
b110100 2
b110100 8
1%
#2640000
0%
#2645000
0'
0!
b10010010 6
b10 :
17
b0 8
11
b0 2
1%
#2650000
0%
#2655000
b1 2
b1 8
1%
#2660000
0%
#2665000
b10 8
b10 2
1%
#2670000
0%
#2675000
b11 2
b11 8
1%
#2680000
0%
#2685000
b100 8
b100 2
1%
#2690000
0%
#2695000
b101 2
b101 8
1%
#2700000
0%
#2705000
b110 8
b110 2
1%
#2710000
0%
#2715000
b111 2
b111 8
1%
#2720000
0%
#2725000
b1000 8
b1000 2
1%
#2730000
0%
#2735000
b1001 2
b1001 8
1%
#2740000
0%
#2745000
b1010 8
b1010 2
1%
#2750000
0%
#2755000
b1011 2
b1011 8
1%
#2760000
0%
#2765000
b1100 8
b1100 2
1%
#2770000
0%
#2775000
b1101 2
b1101 8
1%
#2780000
0%
#2785000
b1110 8
b1110 2
1%
#2790000
0%
#2795000
b1111 2
b1111 8
1%
#2800000
0%
#2805000
b10000 8
b10000 2
1%
#2810000
0%
#2815000
b10001 2
b10001 8
1%
#2820000
0%
#2825000
b10010 8
b10010 2
1%
#2830000
0%
#2835000
b10011 2
b10011 8
1%
#2840000
0%
#2845000
b10100 8
b10100 2
1%
#2850000
0%
#2855000
b10101 2
b10101 8
1%
#2860000
0%
#2865000
b10110 8
b10110 2
1%
#2870000
0%
#2875000
b10111 2
b10111 8
1%
#2880000
0%
#2885000
b11000 8
b11000 2
1%
#2890000
0%
#2895000
b11001 2
b11001 8
1%
#2900000
0%
#2905000
b11010 8
b11010 2
1%
#2910000
0%
#2915000
b11011 2
b11011 8
1%
#2920000
0%
#2925000
b11100 8
b11100 2
1%
#2930000
0%
#2935000
b11101 2
b11101 8
1%
#2940000
0%
#2945000
b11110 8
b11110 2
1%
#2950000
0%
#2955000
b11111 2
b11111 8
1%
#2960000
0%
#2965000
b100000 8
b100000 2
1%
#2970000
0%
#2975000
b100001 2
b100001 8
1%
#2980000
0%
#2985000
b100010 8
b100010 2
1%
#2990000
0%
#2995000
b100011 2
b100011 8
1%
#3000000
0%
#3005000
b100100 8
b100100 2
1%
#3010000
0%
#3015000
b100101 2
b100101 8
1%
#3020000
0%
#3025000
b100110 8
b100110 2
1%
#3030000
0%
#3035000
b100111 2
b100111 8
1%
#3040000
0%
#3045000
b101000 8
b101000 2
1%
#3050000
0%
#3055000
b101001 2
b101001 8
1%
#3060000
0%
#3065000
b101010 8
b101010 2
1%
#3070000
0%
#3075000
b101011 2
b101011 8
1%
#3080000
0%
#3085000
b101100 8
b101100 2
1%
#3090000
0%
#3095000
b101101 2
b101101 8
1%
#3100000
0%
#3105000
b101110 8
b101110 2
1%
#3110000
0%
#3115000
b101111 2
b101111 8
1%
#3120000
0%
#3125000
b110000 8
b110000 2
1%
#3130000
0%
#3135000
b110001 2
b110001 8
1%
#3140000
0%
#3145000
b110010 8
b110010 2
1%
#3150000
0%
#3155000
b110011 2
b110011 8
1%
#3160000
0%
#3165000
b110100 8
b110100 2
1%
#3170000
0%
#3175000
01
b0 2
07
b0 8
1%
#3180000
0%
#3185000
b1 8
b1 2
1%
#3190000
0%
#3195000
b10 2
b10 8
1%
#3200000
0%
#3205000
b11 8
b11 2
1%
#3210000
0%
#3215000
b100 2
b100 8
1%
#3220000
0%
#3225000
b101 8
b101 2
1%
#3230000
0%
#3235000
b110 2
b110 8
1%
#3240000
0%
#3245000
b111 8
b111 2
1%
#3250000
0%
#3255000
b1000 2
b1000 8
1%
#3260000
0%
#3265000
b1001 8
b1001 2
1%
#3270000
0%
#3275000
b1010 2
b1010 8
1%
#3280000
0%
#3285000
b1011 8
b1011 2
1%
#3290000
0%
#3295000
b1100 2
b1100 8
1%
#3300000
0%
#3305000
b1101 8
b1101 2
1%
#3310000
0%
#3315000
b1110 2
b1110 8
1%
#3320000
0%
#3325000
b1111 8
b1111 2
1%
#3330000
0%
#3335000
b10000 2
b10000 8
1%
#3340000
0%
#3345000
b10001 8
b10001 2
1%
#3350000
0%
#3355000
b10010 2
b10010 8
1%
#3360000
0%
#3365000
b10011 8
b10011 2
1%
#3370000
0%
#3375000
b10100 2
b10100 8
1%
#3380000
0%
#3385000
b10101 8
b10101 2
1%
#3390000
0%
#3395000
b10110 2
b10110 8
1%
#3400000
0%
#3405000
b10111 8
b10111 2
1%
#3410000
0%
#3415000
b11000 2
b11000 8
1%
#3420000
0%
#3425000
b11001 8
b11001 2
1%
#3430000
0%
#3435000
b11010 2
b11010 8
1%
#3440000
0%
#3445000
b11011 8
b11011 2
1%
#3450000
0%
#3455000
b11100 2
b11100 8
1%
#3460000
0%
#3465000
b11101 8
b11101 2
1%
#3470000
0%
#3475000
b11110 2
b11110 8
1%
#3480000
0%
#3485000
b11111 8
b11111 2
1%
#3490000
0%
#3495000
b100000 2
b100000 8
1%
#3500000
0%
#3505000
b100001 8
b100001 2
1%
#3510000
0%
#3515000
b100010 2
b100010 8
1%
#3520000
0%
#3525000
b100011 8
b100011 2
1%
#3530000
0%
#3535000
b100100 2
b100100 8
1%
#3540000
0%
#3545000
b100101 8
b100101 2
1%
#3550000
0%
#3555000
b100110 2
b100110 8
1%
#3560000
0%
#3565000
b100111 8
b100111 2
1%
#3570000
0%
#3575000
b101000 2
b101000 8
1%
#3580000
0%
#3585000
b101001 8
b101001 2
1%
#3590000
0%
#3595000
b101010 2
b101010 8
1%
#3600000
0%
#3605000
b101011 8
b101011 2
1%
#3610000
0%
#3615000
b101100 2
b101100 8
1%
#3620000
0%
#3625000
b101101 8
b101101 2
1%
#3630000
0%
#3635000
b101110 2
b101110 8
1%
#3640000
0%
#3645000
b101111 8
b101111 2
1%
#3650000
0%
#3655000
b110000 2
b110000 8
1%
#3660000
0%
#3665000
b110001 8
b110001 2
1%
#3670000
0%
#3675000
b110010 2
b110010 8
1%
#3680000
0%
#3685000
b110011 8
b110011 2
1%
#3690000
0%
#3695000
b110100 2
b110100 8
1%
#3700000
0%
#3705000
b1 9
b0 -
17
b0 8
11
b0 2
1%
#3710000
0%
#3715000
b1 2
b1 8
1%
#3720000
0%
#3725000
b10 8
b10 2
1%
#3730000
0%
#3735000
b11 2
b11 8
1%
#3740000
0%
#3745000
b100 8
b100 2
1%
#3750000
0%
#3755000
b101 2
b101 8
1%
#3760000
0%
#3765000
b110 8
b110 2
1%
#3770000
0%
#3775000
b111 2
b111 8
1%
#3780000
0%
#3785000
b1000 8
b1000 2
1%
#3790000
0%
#3795000
b1001 2
b1001 8
1%
#3800000
0%
#3805000
b1010 8
b1010 2
1%
#3810000
0%
#3815000
b1011 2
b1011 8
1%
#3820000
0%
#3825000
b1100 8
b1100 2
1%
#3830000
0%
#3835000
b1101 2
b1101 8
1%
#3840000
0%
#3845000
b1110 8
b1110 2
1%
#3850000
0%
#3855000
b1111 2
b1111 8
1%
#3860000
0%
#3865000
b10000 8
b10000 2
1%
#3870000
0%
#3875000
b10001 2
b10001 8
1%
#3880000
0%
#3885000
b10010 8
b10010 2
1%
#3890000
0%
#3895000
b10011 2
b10011 8
1%
#3900000
0%
#3905000
b10100 8
b10100 2
1%
#3910000
0%
#3915000
b10101 2
b10101 8
1%
#3920000
0%
#3925000
b10110 8
b10110 2
1%
#3930000
0%
#3935000
b10111 2
b10111 8
1%
#3940000
0%
#3945000
b11000 8
b11000 2
1%
#3950000
0%
#3955000
b11001 2
b11001 8
1%
#3960000
0%
#3965000
b11010 8
b11010 2
1%
#3970000
0%
#3975000
b11011 2
b11011 8
1%
#3980000
0%
#3985000
b11100 8
b11100 2
1%
#3990000
0%
#3995000
b11101 2
b11101 8
1%
#4000000
0%
#4005000
b11110 8
b11110 2
1%
#4010000
0%
#4015000
b11111 2
b11111 8
1%
#4020000
0%
