UpCounter_3bit.v
module UpCounter_3bit(data_in, load_en, clk, reset_n, q_out);

    input [2:0] data_in;
    input load_en, clk, reset_n;
    output reg [2:0] q_out;

    always @(posedge clk or negedge reset_n) begin

        if (~reset_n)
            q_out <= 3'b000;
        else if (load_en)
            q_out <= data_in;
        else
            q_out <= q_out + 1'b1;  
    end

endmodule

UpCounter_3bit_tb.v
module tb_UpCounter_3bit();

    reg [2:0] data_in;
    reg clk, reset_n, load_en;
    wire [2:0] q_out;

    UpCounter_3bit DUT (
        .data_in(data_in),
        .load_en(load_en),
        .clk(clk),
        .reset_n(reset_n),
        .q_out(q_out)
    );

    // Clock generation
    initial begin
        clk = 1'b0;
        forever #5 clk = ~clk;
    end

    // VCD dump
    initial begin
        $dumpfile("UpCounter_3bit.vcd");
        $dumpvars(0, tb_UpCounter_3bit);
    end

    // Monitor
    initial begin
        $monitor("Time = %0t | load_en=%b reset_n=%b data_in=%b | q_out=%b",
                  $time, load_en, reset_n, data_in, q_out);
    end

    // Stimulus
    initial begin

        // Step 1: Apply reset
        reset_n = 0; load_en = 0; data_in = 3'b000;
        #12 reset_n = 1; // Release reset

        // Step 2: Normal counting
        #20;

        // Step 3: Load data into counter
        load_en = 1; data_in = 3'b101; 
        #10 load_en = 0;

        // Step 4: Count again
        #30;

        // Step 5: Load again
        load_en = 1; data_in = 3'b011;
        #10 load_en = 0;

        // Step 6: More counting
        #30;

        // Step 7: Reset again
        reset_n = 0;
        #10 reset_n = 1;

        // Continue counting a bit more
        #30;

        $finish;
    end

endmodule

UpCounter_3bit.vcd
$date
	Fri Dec 26 22:45:12 2025
$end
$version
	Icarus Verilog
$end
$timescale
	1s
$end
$scope module tb_UpCounter_3bit $end
$var wire 3 ! q_out [2:0] $end
$var reg 1 " clk $end
$var reg 3 # data_in [2:0] $end
$var reg 1 $ load_en $end
$var reg 1 % reset_n $end
$scope module DUT $end
$var wire 1 " clk $end
$var wire 3 & data_in [2:0] $end
$var wire 1 $ load_en $end
$var wire 1 % reset_n $end
$var reg 3 ' q_out [2:0] $end
$upscope $end
$upscope $end
$enddefinitions $end
#0
$dumpvars
b0 '
b0 &
0%
0$
b0 #
0"
b0 !
$end
#5
1"
#10
0"
#12
1%
#15
b1 !
b1 '
1"
#20
0"
#25
b10 !
b10 '
1"
#30
0"
#32
b101 #
b101 &
1$
#35
b101 !
b101 '
1"
#40
0"
#42
0$
#45
b110 !
b110 '
1"
#50
0"
#55
b111 !
b111 '
1"
#60
0"
#65
b0 !
b0 '
1"
#70
0"
#72
b11 #
b11 &
1$
#75
b11 !
b11 '
1"
#80
0"
#82
0$
#85
b100 !
b100 '
1"
#90
0"
#95
b101 !
b101 '
1"
#100
0"
#105
b110 !
b110 '
1"
#110
0"
#112
b0 !
b0 '
0%
#115
1"
#120
0"
#122
1%
#125
b1 !
b1 '
1"
#130
0"
#135
b10 !
b10 '
1"
#140
0"
#145
b11 !
b11 '
1"
