UpDownCounter_3bit.v
//synchronous up down counter

module UpDownCounter_3bit(up_down, data_in, load_en, clk, reset_n, q_out);

    input [2:0] data_in;
    input up_down, load_en,clk,reset_n;
    output reg [2:0] q_out;

    always @(posedge clk or reset_n) begin
        if (~reset_n)
            q_out <= 3'b000;
        else if (load_en)
            q_out <= data_in;
        else

            if(up_down)
                q_out <= q_out+1'b1;
            else
                q_out <= q_out-1'b1;
    end

endmodule

UpDownCounter_3bit_tb.v
module tb_UpDownCounter_3bit();

    reg [2:0] data_in;
    reg up_down, load_en,clk,reset_n;
    wire [2:0] q_out;

    UpDownCounter_3bit DUT (
        .up_down(up_down), 
        .data_in(data_in), 
        .load_en(load_en), 
        .clk(clk), 
        .reset_n(reset_n), 
        .q_out(q_out)
    );


    initial begin
        $dumpfile("UpDownCounter_3bit.vcd");
        $dumpvars(0,tb_UpDownCounter_3bit);
    end

    initial begin
        clk = 0;
        forever #5 clk = ~clk;
    end

    initial begin
        $monitor("Time=%0t  |  up_down=%d  data_in=%d  load_en=%d  reset_n=%d  q_out=%d  ",
        $time, up_down, data_in, load_en, reset_n, q_out);
    end

    initial begin
        // initial values
        reset_n = 0; up_down = 1; load_en = 0; data_in = 3'b000; #12;

        // release reset
        reset_n = 1; #10;

        // count up for a few cycles
        up_down = 1; load_en = 0; #60;

        // load a value
        data_in = 3'b101; load_en = 1; #10;
        load_en = 0; #10;

        // count up more
        up_down = 1; #30;

        // load another value
        data_in = 3'b010; load_en = 1; #10;
        load_en = 0; #10;

        // now count down
        up_down = 0; #50;

        // reset again mid-way
        reset_n = 0; #10;
        reset_n = 1; #10;

        // count down after reset
        up_down = 0; #40;

        $finish;
    end

endmodule

UpDownCounter_3bit.vcd
$date
	Fri Dec 26 23:28:30 2025
$end
$version
	Icarus Verilog
$end
$timescale
	1s
$end
$scope module tb_UpDownCounter_3bit $end
$var wire 3 ! q_out [2:0] $end
$var reg 1 " clk $end
$var reg 3 # data_in [2:0] $end
$var reg 1 $ load_en $end
$var reg 1 % reset_n $end
$var reg 1 & up_down $end
$scope module DUT $end
$var wire 1 " clk $end
$var wire 3 ' data_in [2:0] $end
$var wire 1 $ load_en $end
$var wire 1 % reset_n $end
$var wire 1 & up_down $end
$var reg 3 ( q_out [2:0] $end
$upscope $end
$upscope $end
$enddefinitions $end
#0
$dumpvars
b0 (
b0 '
1&
0%
0$
b0 #
0"
b0 !
$end
#5
1"
#10
0"
#12
b1 !
b1 (
1%
#15
b10 !
b10 (
1"
#20
0"
#25
b11 !
b11 (
1"
#30
0"
#35
b100 !
b100 (
1"
#40
0"
#45
b101 !
b101 (
1"
#50
0"
#55
b110 !
b110 (
1"
#60
0"
#65
b111 !
b111 (
1"
#70
0"
#75
b0 !
b0 (
1"
#80
0"
#82
1$
b101 #
b101 '
#85
b101 !
b101 (
1"
#90
0"
#92
0$
#95
b110 !
b110 (
1"
#100
0"
#105
b111 !
b111 (
1"
#110
0"
#115
b0 !
b0 (
1"
#120
0"
#125
b1 !
b1 (
1"
#130
0"
#132
1$
b10 #
b10 '
#135
b10 !
b10 (
1"
#140
0"
#142
0$
#145
b11 !
b11 (
1"
#150
0"
#152
0&
#155
b10 !
b10 (
1"
#160
0"
#165
b1 !
b1 (
1"
#170
0"
#175
b0 !
b0 (
1"
#180
0"
#185
b111 !
b111 (
1"
#190
0"
#195
b110 !
b110 (
1"
#200
0"
#202
b0 !
b0 (
0%
#205
1"
#210
0"
#212
b111 !
b111 (
1%
#215
b110 !
b110 (
1"
#220
0"
#225
b101 !
b101 (
1"
#230
0"
#235
b100 !
b100 (
1"
#240
0"
#245
b11 !
b11 (
1"
#250
0"
#255
b10 !
b10 (
1"
